{
  "type": "Feature",
  "properties": {
    "gn:gn_country":"PS",
    "gn:gn_fcode":"PPL",
    "gn:gn_pop":9631,
    "gn:population":9631,
    "iso:country":"PS",
    "name:ara_x_preferred":[
        "\u0627\u0644\u062f\u0648\u062d\u0629"
    ],
    "name:dut_x_preferred":[
        "Al-Dawha"
    ],
    "name:eng_x_preferred":[
        "Al-Dawha"
    ],
    "name:nno_x_preferred":[
        "Al-Dawha"
    ],
    "name:pol_x_preferred":[
        "Ad-Dauha"
    ],
    "qs_pg:aaroncc":"PS",
    "qs_pg:gn_country":"PS",
    "qs_pg:gn_fcode":"PPL",
    "qs_pg:gn_pop":9631,
    "qs_pg:name":"Ad Daw\u1e29ah",
    "qs_pg:photos_9r":0,
    "qs_pg:photos_sr":0,
    "qs_pg:pop_sr":5,
    "qs_pg:qs_pg_placetype":"locality",
    "wof:name":"Ad Daw\u1e29ah",
    "wof:placetype":"locality",
    "wof:population":9631
},
  "geometry": {"coordinates":[35.18047,31.69948],"type":"Point"}
}