{
  "type": "Feature",
  "properties": {
    "gn:admin1_code":"GZ",
    "gn:asciiname":"Gadid",
    "gn:country_code":"PS",
    "gn:dem":51,
    "gn:feature_class":"P",
    "gn:feature_code":"STLMT",
    "gn:name":"Gadid",
    "gn:population":0,
    "gn:timezone":"Asia/Gaza",
    "iso:country":"PS",
    "name:ces_x_preferred":[
        "Gadid"
    ],
    "name:heb_x_preferred":[
        "\u05d2\u05d3\u05d9\u05d3"
    ],
    "wof:name":"Gadid",
    "wof:placetype":"locality"
},
  "geometry": {"coordinates":[34.26667,31.33333],"type":"Point"}
}