{
  "type": "Feature",
  "properties": {
    "gn:country":"PS",
    "gn:fcode":"PPL",
    "gn:population":2040,
    "iso:country":"PS",
    "name:ara_x_preferred":[
        "R\u0101m\u012bn"
    ],
    "name:ara_x_variant":[
        "\u0631\u0627\u0645\u064a\u0646"
    ],
    "name:arz_x_preferred":[
        "\u0631\u0627\u0645\u064a\u0646"
    ],
    "name:cat_x_preferred":[
        "Ramin"
    ],
    "name:eng_x_preferred":[
        "Ramin"
    ],
    "name:heb_x_preferred":[
        "\u05e8\u05de\u05d9\u05df"
    ],
    "name:mal_x_preferred":[
        "\u0d31\u0d2e\u0d3f\u0d7b"
    ],
    "name:nld_x_preferred":[
        "Ramin"
    ],
    "name:nno_x_preferred":[
        "Ramin i Tulkarm"
    ],
    "name:pol_x_preferred":[
        "Ramin"
    ],
    "qs_pg:aaroncc":"PS",
    "qs_pg:gn_country":"PS",
    "qs_pg:gn_fcode":"PPL",
    "qs_pg:gn_pop":2040,
    "qs_pg:name":"R\u0101m\u012bn",
    "qs_pg:photos_9r":0,
    "qs_pg:photos_sr":0,
    "qs_pg:pop_sr":4,
    "qs_pg:qs_pg_placetype":"locality",
    "wof:name":"R\u0101m\u012bn",
    "wof:placetype":"locality",
    "wof:population":2040
},
  "geometry": {"coordinates":[35.14951,32.2852],"type":"Point"}
}