{
  "type": "Feature",
  "properties": {
    "gn:country":"PS",
    "gn:fcode":"PPL",
    "gn:population":27616,
    "iso:country":"PS",
    "name:ara_x_preferred":[
        "\u0627\u0644\u0638\u0627\u0647\u0631\u064a\u0629"
    ],
    "name:cat_x_preferred":[
        "Ad-Dhahiriya"
    ],
    "name:ceb_x_preferred":[
        "Az\u0327 Z\u0327\u0101hir\u012byah"
    ],
    "name:ces_x_preferred":[
        "Az-Z\u00e1hir\u00edja"
    ],
    "name:ces_x_variant":[
        "az-Z\u00e1hir\u00edja"
    ],
    "name:eng_x_preferred":[
        "Ad-Dhahiriya"
    ],
    "name:eng_x_variant":[
        "ad-Dhahiriya"
    ],
    "name:fas_x_preferred":[
        "\u0627\u0644\u0638\u0627\u0647\u0631\u06cc\u0647"
    ],
    "name:fra_x_preferred":[
        "Ad-Dhahiriya"
    ],
    "name:heb_x_preferred":[
        "\u05d3\u05d0\u05d4\u05e8\u05d9\u05d9\u05d4"
    ],
    "name:ita_x_preferred":[
        "Al-Zahiriyya"
    ],
    "name:jpn_x_preferred":[
        "\u30a2\u30c9\u30fb\u30c0\u30d2\u30ea\u30e4"
    ],
    "name:nld_x_preferred":[
        "Ad-Dhahiriya"
    ],
    "name:nno_x_preferred":[
        "Ad-Dhahiriya"
    ],
    "name:pnb_x_preferred":[
        "\u0627\u0644\u0638\u0627\u06c1\u0631\u06cc\u06c1"
    ],
    "name:pol_x_preferred":[
        "Az-Zahirija"
    ],
    "name:spa_x_preferred":[
        "Ad-Dhahiriya"
    ],
    "name:und_x_variant":[
        "Ed Dhaherie"
    ],
    "name:urd_x_preferred":[
        "\u0627\u0644\u0638\u0627\u06c1\u0631\u06cc\u06c1"
    ],
    "qs_pg:aaroncc":"PS",
    "qs_pg:gn_country":"PS",
    "qs_pg:gn_fcode":"PPL",
    "qs_pg:gn_pop":27616,
    "qs_pg:name":"Az\u0327 Z\u0327\u0101hir\u012byah",
    "qs_pg:photos_9r":0,
    "qs_pg:photos_sr":0,
    "qs_pg:pop_sr":7,
    "qs_pg:qs_pg_placetype":"locality",
    "wof:name":"Az\u0327 Z\u0327\u0101hir\u012byah",
    "wof:placetype":"locality",
    "wof:population":27616
},
  "geometry": {"coordinates":[34.97329,31.40967],"type":"Point"}
}