{
  "type": "Feature",
  "properties": {
    "gn:gn_country":"PS",
    "gn:gn_fcode":"PPL",
    "gn:gn_pop":267,
    "gn:population":267,
    "iso:country":"PS",
    "name:unk_x_variant":[
        "Ezbet Al-Modawar"
    ],
    "qs_pg:aaroncc":"PS",
    "qs_pg:gn_country":"PS",
    "qs_pg:gn_fcode":"PPL",
    "qs_pg:gn_pop":267,
    "qs_pg:name":"al-Mudawwar",
    "qs_pg:photos_9r":0,
    "qs_pg:photos_sr":0,
    "qs_pg:pop_sr":2,
    "qs_pg:qs_pg_placetype":"locality",
    "wof:name":"al-Mudawwar",
    "wof:placetype":"locality",
    "wof:population":267
},
  "geometry": {"coordinates":[35.01221,32.14318],"type":"Point"}
}