{
  "type": "Feature",
  "properties": {
    "gn:admin1_code":"WE",
    "gn:asciiname":"Mevo Dotan",
    "gn:country_code":"PS",
    "gn:dem":278,
    "gn:feature_class":"P",
    "gn:feature_code":"STLMT",
    "gn:name":"Mevo Dotan",
    "gn:population":0,
    "gn:timezone":"Asia/Hebron",
    "iso:country":"PS",
    "wof:name":"Mevo Dotan",
    "wof:placetype":"locality"
},
  "geometry": {"coordinates":[35.16667,32.41667],"type":"Point"}
}