{
  "type": "Feature",
  "properties": {
    "gn:admin1_code":"WE",
    "gn:asciiname":"Yaqqir",
    "gn:country_code":"PS",
    "gn:dem":383,
    "gn:feature_class":"P",
    "gn:feature_code":"STLMT",
    "gn:name":"Yaqqir",
    "gn:population":0,
    "gn:timezone":"Asia/Hebron",
    "iso:country":"PS",
    "wof:name":"Yaqqir",
    "wof:placetype":"locality"
},
  "geometry": {"coordinates":[35.11667,32.15],"type":"Point"}
}