{
  "type": "Feature",
  "properties": {
    "gn:admin1_code":"WE",
    "gn:asciiname":"Abu Salman",
    "gn:country_code":"PS",
    "gn:dem":145,
    "gn:feature_class":"P",
    "gn:feature_code":"PPL",
    "gn:name":"Abu Salman",
    "gn:population":0,
    "gn:timezone":"Asia/Hebron",
    "iso:country":"PS",
    "name:und_x_variant":[
        "Ezbet Salman"
    ],
    "wof:name":"Abu Salman",
    "wof:placetype":"locality"
},
  "geometry": {"coordinates":[35.00576,32.15089],"type":"Point"}
}