{
  "type": "Feature",
  "properties": {
    "gn:gn_country":"PS",
    "gn:gn_fcode":"PPL",
    "gn:gn_pop":835,
    "gn:population":835,
    "iso:country":"PS",
    "name:ara_x_preferred":[
        "Z\u012bf"
    ],
    "name:ara_x_variant":[
        "\u0632\u064a\u0641"
    ],
    "name:eng_x_preferred":[
        "Zif"
    ],
    "name:nld_x_preferred":[
        "Zif"
    ],
    "name:nno_x_preferred":[
        "Zif i Hebron"
    ],
    "qs_pg:aaroncc":"PS",
    "qs_pg:gn_country":"PS",
    "qs_pg:gn_fcode":"PPL",
    "qs_pg:gn_pop":835,
    "qs_pg:name":"Z\u012bf",
    "qs_pg:photos_9r":0,
    "qs_pg:photos_sr":0,
    "qs_pg:pop_sr":2,
    "qs_pg:qs_pg_placetype":"locality",
    "wof:name":"Z\u012bf",
    "wof:placetype":"locality",
    "wof:population":835
},
  "geometry": {"coordinates":[35.13671,31.46693],"type":"Point"}
}