{
  "type": "Feature",
  "properties": {
    "gn:admin1_code":"WE",
    "gn:asciiname":"Bet Yattir",
    "gn:country_code":"PS",
    "gn:dem":786,
    "gn:feature_class":"P",
    "gn:feature_code":"STLMT",
    "gn:name":"Bet Yattir",
    "gn:population":0,
    "gn:timezone":"Asia/Hebron",
    "iso:country":"PS",
    "wof:name":"Bet Yattir",
    "wof:placetype":"locality"
},
  "geometry": {"coordinates":[35.10002,31.34959000000001],"type":"Point"}
}