{
  "type": "Feature",
  "properties": {
    "iso:country":"PS",
    "name:ara_x_preferred":[
        "\u0633\u0644\u0648\u0627\u0646"
    ],
    "name:ces_x_preferred":[
        "Silvan"
    ],
    "name:deu_x_preferred":[
        "Silwan"
    ],
    "name:eng_x_preferred":[
        "Silwan"
    ],
    "name:fin_x_preferred":[
        "Silwan"
    ],
    "name:fra_x_preferred":[
        "Silwan"
    ],
    "name:heb_x_preferred":[
        "\u05e1\u05d9\u05dc\u05d5\u05d0\u05df"
    ],
    "name:ind_x_preferred":[
        "Silwan"
    ],
    "name:mkd_x_preferred":[
        "\u0421\u0438\u043b\u0432\u0430\u043d"
    ],
    "name:nld_x_preferred":[
        "Silwan"
    ],
    "name:rus_x_preferred":[
        "\u0421\u0438\u043b\u044c\u0432\u0430\u043d"
    ],
    "name:spa_x_preferred":[
        "Silwan"
    ],
    "name:swe_x_preferred":[
        "Silwan"
    ],
    "name:urd_x_preferred":[
        "\u0633\u0644\u0648\u0627\u0646"
    ],
    "qs:a0":"Palestine",
    "qs:a0_lc":"PSE",
    "qs:a1":"*",
    "qs:a1r":"*",
    "qs:adm0":"Palestine",
    "qs:la_lc":"*",
    "qs:level":"locality",
    "qs:loc":"Silwan",
    "qs:pop":0,
    "qs:type":"Built-Up Area",
    "wd:wordcount":5649,
    "wof:name":"Silwan",
    "wof:placetype":"neighbourhood"
},
  "geometry": {"coordinates":[35.238664,31.769824],"type":"Point"}
}