{
  "type": "Feature",
  "properties": {
    "gn:country":"PS",
    "gn:fcode":"PPL",
    "gn:population":1214,
    "iso:country":"PS",
    "name:ara_x_preferred":[
        "\u0628\u064a\u062a \u062a\u0639\u0645\u0631"
    ],
    "name:cat_x_preferred":[
        "Beit Ta'mir"
    ],
    "name:eng_x_preferred":[
        "Beit Ta'mir"
    ],
    "name:heb_x_preferred":[
        "\u05d1\u05d9\u05ea \u05ea\u05de\u05d9\u05e8"
    ],
    "name:nld_x_preferred":[
        "Beit Ta'mir"
    ],
    "name:nno_x_preferred":[
        "Beit Ta'mir"
    ],
    "name:und_x_variant":[
        "Khirbat Beit Ta\u2018mir"
    ],
    "qs_pg:aaroncc":"PS",
    "qs_pg:gn_country":"PS",
    "qs_pg:gn_fcode":"PPL",
    "qs_pg:gn_pop":1214,
    "qs_pg:name":"Bayt Ta\u2018mar",
    "qs_pg:photos_9r":0,
    "qs_pg:photos_sr":0,
    "qs_pg:pop_sr":3,
    "qs_pg:qs_pg_placetype":"locality",
    "wof:name":"Bayt Ta\u2018mar",
    "wof:placetype":"locality",
    "wof:population":1214
},
  "geometry": {"coordinates":[35.23986,31.67927],"type":"Point"}
}