{
  "type": "Feature",
  "properties": {
    "gn:admin1_code":"GZ",
    "gn:asciiname":"Qa` al Kharabah",
    "gn:country_code":"PS",
    "gn:dem":53,
    "gn:feature_class":"P",
    "gn:feature_code":"PPL",
    "gn:name":"Q\u0101\u2018 al Khar\u0101bah",
    "gn:population":0,
    "gn:timezone":"Asia/Gaza",
    "iso:country":"PS",
    "name:ara_x_preferred":[
        "\u0642\u0627\u0639 \u0627\u0644\u062e\u064e\u0631\u0627\u0628\u064e\u0629"
    ],
    "name:und_x_variant":[
        "Qa\u2018 el-Kharaba",
        "Q\u0101\u2018 al Khar\u0101bah",
        "Qa\u2018 al Khar\u0101bah"
    ],
    "wof:name":"Qa` al Kharabah",
    "wof:placetype":"locality"
},
  "geometry": {"coordinates":[34.30565,31.30899],"type":"Point"}
}