{
  "type": "Feature",
  "properties": {
    "gn:gn_country":"PS",
    "gn:gn_fcode":"PPL",
    "gn:gn_pop":367,
    "gn:population":367,
    "iso:country":"PS",
    "name:ara_x_preferred":[
        "\u0628\u064a\u062a \u0627\u0644\u0631\u0648\u0634 \u0627\u0644\u062a\u062d\u062a\u0627"
    ],
    "name:unk_x_variant":[
        "Khirbat ar Rawsh at Ta\u1e29t\u0101"
    ],
    "qs_pg:aaroncc":"PS",
    "qs_pg:gn_country":"PS",
    "qs_pg:gn_fcode":"PPL",
    "qs_pg:gn_pop":367,
    "qs_pg:name":"Bayt ar R\u016bsh at Ta\u1e29t\u0101",
    "qs_pg:photos_9r":0,
    "qs_pg:photos_sr":0,
    "qs_pg:pop_sr":2,
    "qs_pg:qs_pg_placetype":"locality",
    "wof:name":"Bayt ar R\u016bsh at Ta\u1e29t\u0101",
    "wof:placetype":"locality",
    "wof:population":367
},
  "geometry": {"coordinates":[34.93595,31.46338],"type":"Point"}
}