{
  "type": "Feature",
  "properties": {
    "gn:gn_country":"PS",
    "gn:gn_fcode":"PPL",
    "gn:gn_pop":5441,
    "gn:population":5441,
    "iso:country":"PS",
    "name:ara_x_preferred":[
        "\u0628\u0646\u064a \u0632\u064a\u062f"
    ],
    "qs_pg:aaroncc":"PS",
    "qs_pg:gn_country":"PS",
    "qs_pg:gn_fcode":"PPL",
    "qs_pg:gn_pop":5441,
    "qs_pg:name":"Ban\u012b Zayd",
    "qs_pg:photos_9r":0,
    "qs_pg:photos_sr":0,
    "qs_pg:pop_sr":5,
    "qs_pg:qs_pg_placetype":"locality",
    "wof:name":"Ban\u012b Zayd",
    "wof:placetype":"locality",
    "wof:population":5441
},
  "geometry": {"coordinates":[35.10316,32.03924],"type":"Point"}
}