{
  "type": "Feature",
  "properties": {
    "gn:admin1_code":"WE",
    "gn:asciiname":"Niriyya",
    "gn:country_code":"PS",
    "gn:dem":177,
    "gn:feature_class":"P",
    "gn:feature_code":"STLMT",
    "gn:name":"Niriyya",
    "gn:population":0,
    "gn:timezone":"Asia/Hebron",
    "iso:country":"PS",
    "wof:name":"Niriyya",
    "wof:placetype":"locality"
},
  "geometry": {"coordinates":[35.05,32.13333],"type":"Point"}
}