{
  "type": "Feature",
  "properties": {
    "gn:admin1_code":"WE",
    "gn:asciiname":"Oranit",
    "gn:country_code":"PS",
    "gn:dem":120,
    "gn:feature_class":"P",
    "gn:feature_code":"STLMT",
    "gn:name":"Oranit",
    "gn:population":0,
    "gn:timezone":"Asia/Hebron",
    "iso:country":"PS",
    "name:rus_x_preferred":[
        "\u041e\u0440\u0430\u043d\u0438\u0442"
    ],
    "name:swe_x_preferred":[
        "Oranit"
    ],
    "wof:name":"Oranit",
    "wof:placetype":"locality"
},
  "geometry": {"coordinates":[34.99097,32.13265999999999],"type":"Point"}
}