{
  "type": "Feature",
  "properties": {
    "gn:admin1_code":"WE",
    "gn:admin2_code":"7870644",
    "gn:asciiname":"Ilar",
    "gn:country_code":"PS",
    "gn:dem":229,
    "gn:feature_class":"P",
    "gn:feature_code":"PPL",
    "gn:name":"Ilar",
    "gn:population":0,
    "gn:timezone":"Asia/Hebron",
    "iso:country":"PS",
    "name:und_x_variant":[
        "Ellar",
        "Illar"
    ],
    "wof:name":"Ilar",
    "wof:placetype":"locality"
},
  "geometry": {"coordinates":[35.10865,32.3707],"type":"Point"}
}