{
  "type": "Feature",
  "properties": {
    "gn:gn_country":"PS",
    "gn:gn_fcode":"PPL",
    "gn:gn_pop":59504,
    "gn:population":59504,
    "iso:country":"PS",
    "name:ara_x_preferred":[
        "\u062f\u064a\u0631 \u0627\u0644\u0628\u0644\u062d"
    ],
    "name:eng_x_preferred":[
        "Deir el-Balah"
    ],
    "name:nno_x_preferred":[
        "Deir el-Balah"
    ],
    "name:nor_x_preferred":[
        "Deir el-Balah"
    ],
    "name:unk_x_variant":[
        "Deir el-Balah"
    ],
    "qs_pg:aaroncc":"PS",
    "qs_pg:gn_country":"PS",
    "qs_pg:gn_fcode":"PPL",
    "qs_pg:gn_pop":59504,
    "qs_pg:name":"Dayr al Bala\u1e29",
    "qs_pg:photos_9r":0,
    "qs_pg:photos_sr":0,
    "qs_pg:pop_sr":8,
    "qs_pg:qs_pg_placetype":"locality",
    "wof:name":"Dayr al Bala\u1e29",
    "wof:placetype":"locality",
    "wof:population":59504
},
  "geometry": {"coordinates":[34.35033,31.41783],"type":"Point"}
}