{
  "type": "Feature",
  "properties": {
    "gn:admin1_code":"WE",
    "gn:asciiname":"Qiryat Sefer",
    "gn:country_code":"PS",
    "gn:dem":274,
    "gn:feature_class":"P",
    "gn:feature_code":"STLMT",
    "gn:name":"Qiryat Sefer",
    "gn:population":0,
    "gn:timezone":"Asia/Hebron",
    "iso:country":"PS",
    "wof:name":"Qiryat Sefer",
    "wof:placetype":"locality"
},
  "geometry": {"coordinates":[35.03333,31.93333],"type":"Point"}
}