{
  "type": "Feature",
  "properties": {
    "gn:country":"PS",
    "gn:fcode":"PPL",
    "gn:population":753,
    "iso:country":"PS",
    "name:ara_x_preferred":[
        "\u0633\u0641\u0627\u0631\u064a\u0646"
    ],
    "name:cat_x_preferred":[
        "Saffarin"
    ],
    "name:ceb_x_preferred":[
        "Saff\u0101r\u012bn"
    ],
    "name:eng_x_preferred":[
        "Saffarin"
    ],
    "name:heb_x_preferred":[
        "\u05e1\u05e4\u05d0\u05e8\u05d9\u05df"
    ],
    "name:nld_x_preferred":[
        "Saffarin"
    ],
    "name:nno_x_preferred":[
        "Saffarin"
    ],
    "name:pol_x_preferred":[
        "Saffarin"
    ],
    "name:urd_x_preferred":[
        "\u0633\u0641\u0627\u0631\u064a\u0646"
    ],
    "qs_pg:aaroncc":"PS",
    "qs_pg:gn_country":"PS",
    "qs_pg:gn_fcode":"PPL",
    "qs_pg:gn_pop":753,
    "qs_pg:name":"Saff\u0101r\u012bn",
    "qs_pg:photos_9r":0,
    "qs_pg:photos_sr":0,
    "qs_pg:pop_sr":2,
    "qs_pg:qs_pg_placetype":"locality",
    "wof:name":"Saff\u0101r\u012bn",
    "wof:placetype":"locality",
    "wof:population":753
},
  "geometry": {"coordinates":[35.11028,32.26225],"type":"Point"}
}