{
  "type": "Feature",
  "properties": {
    "gn:admin1_code":"WE",
    "gn:asciiname":"Efrata",
    "gn:cc2":"PS",
    "gn:country_code":"PS",
    "gn:dem":929,
    "gn:feature_class":"P",
    "gn:feature_code":"STLMT",
    "gn:name":"Efrata",
    "gn:population":0,
    "gn:timezone":"Asia/Hebron",
    "iso:country":"PS",
    "name:ara_x_preferred":[
        "\u0623\u0641\u0631\u0627\u062a"
    ],
    "name:cat_x_preferred":[
        "Efrat"
    ],
    "name:ces_x_preferred":[
        "Efrat"
    ],
    "name:deu_x_preferred":[
        "Efrata"
    ],
    "name:fas_x_preferred":[
        "\u0627\u0641\u0631\u0627\u062a"
    ],
    "name:fra_x_preferred":[
        "Efrat"
    ],
    "name:heb_x_preferred":[
        "\u05d0\u05e4\u05e8\u05ea"
    ],
    "name:ita_x_preferred":[
        "Efrat"
    ],
    "name:nld_x_preferred":[
        "Efrat"
    ],
    "name:nno_x_preferred":[
        "Efrat"
    ],
    "name:nor_x_preferred":[
        "Efrat"
    ],
    "name:pol_x_preferred":[
        "Efrat"
    ],
    "name:rus_x_preferred":[
        "\u042d\u0444\u0440\u0430\u0442"
    ],
    "name:spa_x_preferred":[
        "Efrat"
    ],
    "name:tur_x_preferred":[
        "Efrat"
    ],
    "name:und_x_variant":[
        "Efratah"
    ],
    "wof:name":"Efrata",
    "wof:placetype":"locality"
},
  "geometry": {"coordinates":[35.13333,31.65],"type":"Point"}
}