{
  "type": "Feature",
  "properties": {
    "gn:admin1_code":"WE",
    "gn:asciiname":"Efrata",
    "gn:cc2":"PS",
    "gn:country_code":"PS",
    "gn:dem":929,
    "gn:feature_class":"P",
    "gn:feature_code":"STLMT",
    "gn:name":"Efrata",
    "gn:population":0,
    "gn:timezone":"Asia/Hebron",
    "iso:country":"PS",
    "name:und_x_variant":[
        "Efratah",
        "Efrata"
    ],
    "wof:name":"Efrata",
    "wof:placetype":"locality"
},
  "geometry": {"coordinates":[35.13333,31.65],"type":"Point"}
}