{
  "type": "Feature",
  "properties": {
    "gn:admin1_code":"00",
    "gn:asciiname":"Al `Azazimah",
    "gn:country_code":"PS",
    "gn:dem":533,
    "gn:feature_class":"P",
    "gn:feature_code":"PPL",
    "gn:name":"Al \u2018Az\u0101zimah",
    "gn:population":0,
    "gn:timezone":"Asia/Hebron",
    "iso:country":"PS",
    "name:ara_x_preferred":[
        "\u0627\u0644\u0639\u0632\u0627\u0632\u0645\u0629"
    ],
    "name:und_x_variant":[
        "Al \u2018Az\u0101zimah"
    ],
    "wof:name":"Al `Azazimah",
    "wof:placetype":"locality"
},
  "geometry": {"coordinates":[35.2358,31.5633],"type":"Point"}
}