{
  "type": "Feature",
  "properties": {
    "gn:gn_country":"PS",
    "gn:gn_fcode":"PPL",
    "gn:gn_pop":1456,
    "gn:population":1456,
    "iso:country":"PS",
    "name:ara_x_preferred":[
        "\u0627\u0644\u0644\u0628\u0646 \u0627\u0644\u063a\u0631\u0628\u064a"
    ],
    "name:eng_x_preferred":[
        "Al-Lubban al-Gharbi"
    ],
    "name:fas_x_preferred":[
        "\u0627\u0644-\u0644\u0648\u0628\u0627\u0646 \u0627\u0644-\u0642\u0631\u06cc\u0628"
    ],
    "name:heb_x_preferred":[
        "\u05d0-\u05dc\u05d5\u05d1\u05df \u05d0\u05dc-\u05e2'\u05e8\u05d1\u05d9"
    ],
    "name:nld_x_preferred":[
        "Al-Lubban al-Gharbi"
    ],
    "name:nno_x_preferred":[
        "Al-Lubban al-Gharbi"
    ],
    "name:unk_x_variant":[
        "Lubban"
    ],
    "qs_pg:aaroncc":"PS",
    "qs_pg:gn_country":"PS",
    "qs_pg:gn_fcode":"PPL",
    "qs_pg:gn_pop":1456,
    "qs_pg:name":"Al Lubban al Gharb\u012b",
    "qs_pg:photos_9r":0,
    "qs_pg:photos_sr":0,
    "qs_pg:pop_sr":3,
    "qs_pg:qs_pg_placetype":"locality",
    "wof:name":"Al Lubban al Gharb\u012b",
    "wof:placetype":"locality",
    "wof:population":1456
},
  "geometry": {"coordinates":[35.03928,32.03504],"type":"Point"}
}