{
  "type": "Feature",
  "properties": {
    "gn:admin1_code":"00",
    "gn:asciiname":"Al Mas`udiyah",
    "gn:country_code":"PS",
    "gn:dem":282,
    "gn:feature_class":"P",
    "gn:feature_code":"PPL",
    "gn:name":"Al Mas\u2018\u016bd\u012byah",
    "gn:population":0,
    "gn:timezone":"Asia/Hebron",
    "iso:country":"PS",
    "name:ara_x_preferred":[
        "\u0627\u0644\u0645\u0633\u0639\u0648\u062f\u064a\u0629"
    ],
    "name:und_x_variant":[
        "Al Mas\u2018\u016bd\u012byah"
    ],
    "wof:name":"Al Mas`udiyah",
    "wof:placetype":"locality"
},
  "geometry": {"coordinates":[35.1767,32.28207],"type":"Point"}
}