{
  "type": "Feature",
  "properties": {
    "gn:gn_country":"PS",
    "gn:gn_fcode":"PPL",
    "gn:gn_pop":4092,
    "gn:population":4092,
    "iso:country":"PS",
    "name:ara_x_preferred":[
        "\u0628\u062a\u064a\u0631"
    ],
    "name:ben_x_preferred":[
        "\u09ac\u09be\u09a4\u09cd\u09a4\u09bf\u09b0"
    ],
    "name:cat_x_preferred":[
        "Battir"
    ],
    "name:ceb_x_preferred":[
        "Batt\u012br"
    ],
    "name:ces_x_preferred":[
        "Battir"
    ],
    "name:deu_x_preferred":[
        "Battir"
    ],
    "name:eng_x_preferred":[
        "Battir"
    ],
    "name:fas_x_preferred":[
        "\u0628\u062a\u06cc\u0631"
    ],
    "name:fra_x_preferred":[
        "Battir"
    ],
    "name:heb_x_preferred":[
        "\u05d1\u05ea\u05d9\u05e8"
    ],
    "name:hrv_x_preferred":[
        "Battir"
    ],
    "name:ind_x_preferred":[
        "Battir"
    ],
    "name:ita_x_preferred":[
        "Battir"
    ],
    "name:jpn_x_preferred":[
        "\u30d0\u30c6\u30a3\u30a2"
    ],
    "name:kat_x_preferred":[
        "\u10d1\u10d0\u10e2\u10d8\u10e0\u10d8"
    ],
    "name:mal_x_preferred":[
        "\u0d2c\u0d3e\u0d1f\u0d4d\u0d1f\u0d3f\u0d7c"
    ],
    "name:nld_x_preferred":[
        "Battir"
    ],
    "name:nno_x_preferred":[
        "Battir"
    ],
    "name:pol_x_preferred":[
        "Battir"
    ],
    "name:por_x_preferred":[
        "Battir"
    ],
    "name:rus_x_preferred":[
        "\u0411\u0430\u0442\u0442\u0438\u0440"
    ],
    "name:spa_x_preferred":[
        "Battir"
    ],
    "name:tur_x_preferred":[
        "Battir"
    ],
    "name:unk_x_variant":[
        "Betar"
    ],
    "name:vie_x_preferred":[
        "Battir"
    ],
    "qs_pg:aaroncc":"PS",
    "qs_pg:gn_country":"PS",
    "qs_pg:gn_fcode":"PPL",
    "qs_pg:gn_pop":4092,
    "qs_pg:name":"Batt\u012br",
    "qs_pg:photos_9r":0,
    "qs_pg:photos_sr":0,
    "qs_pg:pop_sr":4,
    "qs_pg:qs_pg_placetype":"locality",
    "wof:name":"Batt\u012br",
    "wof:placetype":"locality",
    "wof:population":4092
},
  "geometry": {"coordinates":[35.14103,31.71945],"type":"Point"}
}