{
  "type": "Feature",
  "properties": {
    "gn:admin1_code":"WE",
    "gn:asciiname":"Na`ale",
    "gn:country_code":"PS",
    "gn:dem":359,
    "gn:feature_class":"P",
    "gn:feature_code":"STLMT",
    "gn:name":"Na\u2018ale",
    "gn:population":0,
    "gn:timezone":"Asia/Hebron",
    "iso:country":"PS",
    "wof:name":"Na`ale",
    "wof:placetype":"locality"
},
  "geometry": {"coordinates":[35.05,31.95],"type":"Point"}
}