{
  "type": "Feature",
  "properties": {
    "gn:gn_country":"PS",
    "gn:gn_fcode":"PPL",
    "gn:gn_pop":2194,
    "gn:population":2194,
    "iso:country":"PS",
    "name:ara_x_preferred":[
        "\u062f\u064a\u0631 \u0627\u0644\u062d\u0637\u0628"
    ],
    "name:cat_x_preferred":[
        "Deir al-Hatab"
    ],
    "name:eng_x_preferred":[
        "Deir al-Hatab"
    ],
    "name:heb_x_preferred":[
        "\u05d3\u05d9\u05e8 \u05d0\u05dc-\u05d7\u05d8\u05d1"
    ],
    "name:nld_x_preferred":[
        "Deir al-Hatab"
    ],
    "name:nno_x_preferred":[
        "Deir al-Hatab"
    ],
    "name:unk_x_variant":[
        "Deir al Hatab"
    ],
    "qs_pg:aaroncc":"PS",
    "qs_pg:gn_country":"PS",
    "qs_pg:gn_fcode":"PPL",
    "qs_pg:gn_pop":2194,
    "qs_pg:name":"Dayr al \u1e28a\u0163ab",
    "qs_pg:photos_9r":0,
    "qs_pg:photos_sr":0,
    "qs_pg:pop_sr":4,
    "qs_pg:qs_pg_placetype":"locality",
    "wof:name":"Dayr al \u1e28a\u0163ab",
    "wof:placetype":"locality",
    "wof:population":2194
},
  "geometry": {"coordinates":[35.32127,32.21734],"type":"Point"}
}