{
  "type": "Feature",
  "properties": {
    "gn:country":"PS",
    "gn:fcode":"PPL",
    "gn:population":171,
    "iso:country":"PS",
    "name:ara_x_preferred":[
        "\u0627\u0644\u0645\u0646\u0635\u0648\u0631\u0629"
    ],
    "qs_pg:aaroncc":"PS",
    "qs_pg:gn_country":"PS",
    "qs_pg:gn_fcode":"PPL",
    "qs_pg:gn_pop":171,
    "qs_pg:name":"Al Man\u015f\u016brah",
    "qs_pg:photos_9r":0,
    "qs_pg:photos_sr":0,
    "qs_pg:pop_sr":1,
    "qs_pg:qs_pg_placetype":"locality",
    "wof:name":"Al Man\u015f\u016brah",
    "wof:placetype":"locality",
    "wof:population":171
},
  "geometry": {"coordinates":[35.21627,32.38653],"type":"Point"}
}