{
  "type": "Feature",
  "properties": {
    "gn:admin1_code":"00",
    "gn:asciiname":"Umm `Aslah",
    "gn:country_code":"PS",
    "gn:dem":536,
    "gn:feature_class":"P",
    "gn:feature_code":"PPL",
    "gn:name":"Umm \u2018Aslah",
    "gn:population":0,
    "gn:timezone":"Asia/Hebron",
    "iso:country":"PS",
    "name:ara_x_preferred":[
        "\u0623\u0645 \u0639\u0633\u0644\u0629"
    ],
    "name:und_x_variant":[
        "Umm \u2018Aslah"
    ],
    "wof:name":"Umm `Aslah",
    "wof:placetype":"locality"
},
  "geometry": {"coordinates":[35.2825,31.69843],"type":"Point"}
}