{
  "type": "Feature",
  "properties": {
    "gn:admin1_code":"WE",
    "gn:asciiname":"al-Shuyukh",
    "gn:country_code":"PS",
    "gn:dem":944,
    "gn:feature_class":"P",
    "gn:feature_code":"PPL",
    "gn:name":"al-Shuyukh",
    "gn:population":0,
    "gn:timezone":"Asia/Hebron",
    "iso:country":"PS",
    "name:und_x_variant":[
        "Al-Shuyoukh",
        "Al-Shoyoukh",
        "alShuyukh"
    ],
    "wof:name":"al-Shuyukh",
    "wof:placetype":"locality"
},
  "geometry": {"coordinates":[35.14942,31.575],"type":"Point"}
}