{
  "type": "Feature",
  "properties": {
    "gn:gn_country":"PS",
    "gn:gn_fcode":"PPL",
    "gn:gn_pop":884,
    "gn:population":884,
    "iso:country":"PS",
    "name:ara_x_preferred":[
        "\u062f\u064a\u0631 \u063a\u0632\u0627\u0644\u0629"
    ],
    "name:cat_x_preferred":[
        "Deir Ghazaleh"
    ],
    "name:dut_x_preferred":[
        "Deir Ghazaleh"
    ],
    "name:eng_x_preferred":[
        "Deir Ghazaleh"
    ],
    "name:nno_x_preferred":[
        "Deir Ghazaleh"
    ],
    "name:pol_x_preferred":[
        "Dajr Ghazala"
    ],
    "name:unk_x_variant":[
        "Deir Ghaz\u0101la"
    ],
    "qs_pg:aaroncc":"PS",
    "qs_pg:gn_country":"PS",
    "qs_pg:gn_fcode":"PPL",
    "qs_pg:gn_pop":884,
    "qs_pg:name":"Dayr Ghaz\u0101lah",
    "qs_pg:photos_9r":0,
    "qs_pg:photos_sr":0,
    "qs_pg:pop_sr":2,
    "qs_pg:qs_pg_placetype":"locality",
    "wof:name":"Dayr Ghaz\u0101lah",
    "wof:placetype":"locality",
    "wof:population":884
},
  "geometry": {"coordinates":[35.35104,32.49586],"type":"Point"}
}