{
  "type": "Feature",
  "properties": {
    "gn:country":"PS",
    "gn:fcode":"PPL",
    "gn:population":889,
    "iso:country":"PS",
    "name:ara_x_preferred":[
        "\u0642\u0644\u0627\u0639 \u0632\u064a\u062a\u0627"
    ],
    "name:und_x_variant":[
        "Khirbat Zeita"
    ],
    "qs_pg:aaroncc":"PS",
    "qs_pg:gn_country":"PS",
    "qs_pg:gn_fcode":"PPL",
    "qs_pg:gn_pop":889,
    "qs_pg:name":"Qil\u0101\u2018 Zayt\u0101",
    "qs_pg:photos_9r":0,
    "qs_pg:photos_sr":0,
    "qs_pg:pop_sr":2,
    "qs_pg:qs_pg_placetype":"locality",
    "wof:name":"Qil\u0101\u2018 Zayt\u0101",
    "wof:placetype":"locality",
    "wof:population":889
},
  "geometry": {"coordinates":[35.12077,31.55294],"type":"Point"}
}