{
  "type": "Feature",
  "properties": {
    "gn:admin1_code":"WE",
    "gn:asciiname":"Khirbat an Nasara",
    "gn:country_code":"PS",
    "gn:dem":1012,
    "gn:feature_class":"P",
    "gn:feature_code":"PPL",
    "gn:name":"Khirbat an Na\u015f\u0101r\u00e1",
    "gn:population":0,
    "gn:timezone":"Asia/Hebron",
    "iso:country":"PS",
    "name:und_x_variant":[
        "Khirbat en Na\u1e63\u0101ra",
        "Khirbat an Na\u015f\u0101r\u00e1"
    ],
    "wof:name":"Khirbat an Nasara",
    "wof:placetype":"locality"
},
  "geometry": {"coordinates":[35.10177,31.553],"type":"Point"}
}