{
  "type": "Feature",
  "properties": {
    "gn:admin1_code":"WE",
    "gn:asciiname":"Bet Horon B",
    "gn:country_code":"PS",
    "gn:dem":591,
    "gn:feature_class":"P",
    "gn:feature_code":"STLMT",
    "gn:name":"Bet H\u0331oron B",
    "gn:population":0,
    "gn:timezone":"Asia/Hebron",
    "iso:country":"PS",
    "wof:name":"Bet Horon B",
    "wof:placetype":"locality"
},
  "geometry": {"coordinates":[35.11667,31.88333],"type":"Point"}
}