{
  "type": "Feature",
  "properties": {
    "gn:gn_country":"PS",
    "gn:gn_fcode":"PPL",
    "gn:gn_pop":6692,
    "gn:population":6692,
    "iso:country":"PS",
    "name:ara_x_preferred":[
        "\u062f\u064a\u0631 \u062f\u0628\u0648\u0627\u0646"
    ],
    "name:cat_x_preferred":[
        "Deir Dibwan"
    ],
    "name:ceb_x_preferred":[
        "Dayr Dibw\u0101n"
    ],
    "name:eng_x_preferred":[
        "Deir Debwan"
    ],
    "name:heb_x_preferred":[
        "\u05d3\u05d9\u05e8 \u05d3\u05d9\u05d1\u05d5\u05d5\u05d0\u05df"
    ],
    "name:nno_x_preferred":[
        "Deir Dibwan"
    ],
    "name:pol_x_preferred":[
        "Dajr Dibwan"
    ],
    "name:unk_x_variant":[
        "Deir Dibw\u0101n"
    ],
    "qs_pg:aaroncc":"PS",
    "qs_pg:gn_country":"PS",
    "qs_pg:gn_fcode":"PPL",
    "qs_pg:gn_pop":6692,
    "qs_pg:name":"Dayr Dibw\u0101n",
    "qs_pg:photos_9r":0,
    "qs_pg:photos_sr":0,
    "qs_pg:pop_sr":5,
    "qs_pg:qs_pg_placetype":"locality",
    "wof:name":"Dayr Dibw\u0101n",
    "wof:placetype":"locality",
    "wof:population":6692
},
  "geometry": {"coordinates":[35.26661,31.91112],"type":"Point"}
}