{
  "type": "Feature",
  "properties": {
    "gn:admin1_code":"WE",
    "gn:asciiname":"Nahal Negohot",
    "gn:cc2":"PS",
    "gn:country_code":"PS",
    "gn:dem":539,
    "gn:feature_class":"P",
    "gn:feature_code":"STLMT",
    "gn:name":"Na\u1e96al Negohot",
    "gn:population":0,
    "gn:timezone":"Asia/Hebron",
    "iso:country":"PS",
    "name:und_x_variant":[
        "Negohot",
        "Na\u1e96al Negohot"
    ],
    "wof:name":"Nahal Negohot",
    "wof:placetype":"locality"
},
  "geometry": {"coordinates":[34.96667,31.48333],"type":"Point"}
}