{
  "type": "Feature",
  "properties": {
    "gn:admin1_code":"WE",
    "gn:asciiname":"Migdal Oz",
    "gn:country_code":"PS",
    "gn:dem":940,
    "gn:feature_class":"P",
    "gn:feature_code":"STLMT",
    "gn:name":"Migdal Oz",
    "gn:population":0,
    "gn:timezone":"Asia/Hebron",
    "iso:country":"PS",
    "name:ara_x_preferred":[
        "\u0645\u062c\u062f\u0627\u0644 \u0639\u0648\u0632"
    ],
    "name:cat_x_preferred":[
        "Migdal Oz"
    ],
    "name:ces_x_preferred":[
        "Migdal Oz"
    ],
    "name:deu_x_preferred":[
        "Migdal Oz"
    ],
    "name:heb_x_preferred":[
        "\u05de\u05d2\u05d3\u05dc \u05e2\u05d5\u05d6"
    ],
    "name:ind_x_preferred":[
        "Migdal Oz"
    ],
    "name:nno_x_preferred":[
        "Migdal Oz"
    ],
    "name:pol_x_preferred":[
        "Migdal Oz"
    ],
    "name:spa_x_preferred":[
        "Migdal Oz"
    ],
    "wof:name":"Migdal Oz",
    "wof:placetype":"locality"
},
  "geometry": {"coordinates":[35.16667,31.65],"type":"Point"}
}