{
  "type": "Feature",
  "properties": {
    "gn:country":"PS",
    "gn:fcode":"PPL",
    "gn:population":5535,
    "iso:country":"PS",
    "name:ara_x_preferred":[
        "\u1e28\u016bs\u0101n"
    ],
    "name:ara_x_variant":[
        "\u062d\u0648\u0633\u0627\u0646"
    ],
    "name:cat_x_preferred":[
        "Husan"
    ],
    "name:ceb_x_preferred":[
        "\u1e28\u016bs\u0101n"
    ],
    "name:eng_x_preferred":[
        "Husan"
    ],
    "name:fra_x_preferred":[
        "Houssane"
    ],
    "name:heb_x_preferred":[
        "\u05d7\u05d5\u05e1\u05d0\u05df"
    ],
    "name:nno_x_preferred":[
        "Husan"
    ],
    "name:pol_x_preferred":[
        "Husan"
    ],
    "name:spa_x_preferred":[
        "Husan"
    ],
    "qs_pg:aaroncc":"PS",
    "qs_pg:gn_country":"PS",
    "qs_pg:gn_fcode":"PPL",
    "qs_pg:gn_pop":5535,
    "qs_pg:name":"\u1e28\u016bs\u0101n",
    "qs_pg:photos_9r":0,
    "qs_pg:photos_sr":0,
    "qs_pg:pop_sr":5,
    "qs_pg:qs_pg_placetype":"locality",
    "wof:name":"\u1e28\u016bs\u0101n",
    "wof:placetype":"locality",
    "wof:population":5535
},
  "geometry": {"coordinates":[35.13475,31.70931],"type":"Point"}
}