{
  "type": "Feature",
  "properties": {
    "gn:admin1_code":"WE",
    "gn:asciiname":"Khirbat al `Alawinah",
    "gn:country_code":"PS",
    "gn:dem":694,
    "gn:feature_class":"P",
    "gn:feature_code":"PPL",
    "gn:name":"Khirbat al \u2018Al\u0101winah",
    "gn:population":0,
    "gn:timezone":"Asia/Hebron",
    "iso:country":"PS",
    "name:und_x_variant":[
        "Khirbat el \u2018Al\u0101wina",
        "Khirbat al \u2018Al\u0101winah"
    ],
    "wof:name":"Khirbat al `Alawinah",
    "wof:placetype":"locality"
},
  "geometry": {"coordinates":[35.18333,31.81667],"type":"Point"}
}