{
  "type": "Feature",
  "properties": {
    "gn:gn_country":"PS",
    "gn:gn_fcode":"PPL",
    "gn:gn_pop":20835,
    "gn:population":20835,
    "iso:country":"PS",
    "name:ara_x_preferred":[
        "\u062f\u0648\u0631\u0627"
    ],
    "name:bul_x_preferred":[
        "\u0414\u0443\u0440\u0430"
    ],
    "name:cat_x_preferred":[
        "Dura"
    ],
    "name:ceb_x_preferred":[
        "D\u016br\u0101"
    ],
    "name:ces_x_preferred":[
        "Dur\u00e1"
    ],
    "name:deu_x_preferred":[
        "Dura"
    ],
    "name:eng_x_preferred":[
        "Dura"
    ],
    "name:fas_x_preferred":[
        "\u062f\u0648\u0631\u0627"
    ],
    "name:fra_x_preferred":[
        "Dura H\u00e9bron"
    ],
    "name:heb_x_preferred":[
        "\u05d3\u05d5\u05e8\u05d0"
    ],
    "name:ind_x_preferred":[
        "Adoraim"
    ],
    "name:ita_x_preferred":[
        "Dura"
    ],
    "name:jpn_x_preferred":[
        "\u30c9\u30a5\u30e9"
    ],
    "name:nld_x_preferred":[
        "Dura"
    ],
    "name:nno_x_preferred":[
        "Dura i Hebron"
    ],
    "name:pol_x_preferred":[
        "Dura"
    ],
    "name:rus_x_preferred":[
        "\u0414\u0443\u0440\u044b"
    ],
    "name:rus_x_variant":[
        "\u0414\u0443\u0440\u0430"
    ],
    "name:spa_x_preferred":[
        "Dura"
    ],
    "name:unk_x_variant":[
        "D\u016brah"
    ],
    "name:urd_x_preferred":[
        "\u062f\u0648\u0631\u0627\u060c \u0627\u0644\u062e\u0644\u06cc\u0644"
    ],
    "name:urd_x_variant":[
        "\u062f\u0648\u0631\u0627"
    ],
    "qs_pg:aaroncc":"PS",
    "qs_pg:gn_country":"PS",
    "qs_pg:gn_fcode":"PPL",
    "qs_pg:gn_pop":20835,
    "qs_pg:name":"D\u016br\u0101",
    "qs_pg:photos_9r":0,
    "qs_pg:photos_sr":0,
    "qs_pg:pop_sr":7,
    "qs_pg:qs_pg_placetype":"locality",
    "wof:name":"D\u016br\u0101",
    "wof:placetype":"locality",
    "wof:population":20835
},
  "geometry": {"coordinates":[35.02929,31.50777],"type":"Point"}
}