{
  "type": "Feature",
  "properties": {
    "gn:country":"PS",
    "gn:fcode":"PPL",
    "gn:population":2008,
    "iso:country":"PS",
    "name:ara_x_preferred":[
        "\u0627\u0644\u0642\u0628\u064a\u0628\u0629"
    ],
    "name:und_x_variant":[
        "Qubeiba"
    ],
    "qs_pg:aaroncc":"PS",
    "qs_pg:gn_country":"PS",
    "qs_pg:gn_fcode":"PPL",
    "qs_pg:gn_pop":2008,
    "qs_pg:name":"Al Qubaybah",
    "qs_pg:photos_9r":0,
    "qs_pg:photos_sr":0,
    "qs_pg:pop_sr":4,
    "qs_pg:qs_pg_placetype":"locality",
    "wof:name":"Al Qubaybah",
    "wof:placetype":"locality",
    "wof:population":2008
},
  "geometry": {"coordinates":[35.13678,31.83886],"type":"Point"}
}