{
  "type": "Feature",
  "properties": {
    "gn:admin1_code":"WE",
    "gn:asciiname":"Hinnanit",
    "gn:country_code":"PS",
    "gn:dem":391,
    "gn:feature_class":"P",
    "gn:feature_code":"STLMT",
    "gn:name":"H\u0331innanit",
    "gn:population":0,
    "gn:timezone":"Asia/Hebron",
    "iso:country":"PS",
    "name:pol_x_preferred":[
        "Chinnanit"
    ],
    "name:und_x_variant":[
        "H\u0331innanit"
    ],
    "wof:name":"Hinnanit",
    "wof:placetype":"locality"
},
  "geometry": {"coordinates":[35.16667,32.46667],"type":"Point"}
}