{
  "type": "Feature",
  "properties": {
    "gn:gn_country":"PS",
    "gn:gn_fcode":"PPL",
    "gn:gn_pop":5730,
    "gn:population":5730,
    "iso:country":"PS",
    "name:ara_x_preferred":[
        "\u0628\u0631\u0642\u064a\u0646"
    ],
    "name:cat_x_preferred":[
        "Burqin"
    ],
    "name:ceb_x_preferred":[
        "Birq\u012bn"
    ],
    "name:deu_x_preferred":[
        "Burqin"
    ],
    "name:eng_x_preferred":[
        "Burqin"
    ],
    "name:fra_x_preferred":[
        "Burquin"
    ],
    "name:heb_x_preferred":[
        "\u05d1\u05d9\u05e8\u05e7\u05d9\u05df"
    ],
    "name:nld_x_preferred":[
        "Burqin"
    ],
    "name:nno_x_preferred":[
        "Burqin"
    ],
    "name:pol_x_preferred":[
        "Burkin"
    ],
    "name:ron_x_preferred":[
        "Burkin"
    ],
    "name:spa_x_preferred":[
        "Burqin"
    ],
    "name:unk_x_variant":[
        "Burq\u012bn"
    ],
    "qs_pg:aaroncc":"PS",
    "qs_pg:gn_country":"PS",
    "qs_pg:gn_fcode":"PPL",
    "qs_pg:gn_pop":5730,
    "qs_pg:name":"Birq\u012bn",
    "qs_pg:photos_9r":0,
    "qs_pg:photos_sr":0,
    "qs_pg:pop_sr":5,
    "qs_pg:qs_pg_placetype":"locality",
    "wof:name":"Birq\u012bn",
    "wof:placetype":"locality",
    "wof:population":5730
},
  "geometry": {"coordinates":[35.26076,32.45461],"type":"Point"}
}