{
  "type": "Feature",
  "properties": {
    "gn:admin1_code":"WE",
    "gn:asciiname":"Tekoa",
    "gn:country_code":"PS",
    "gn:dem":768,
    "gn:feature_class":"P",
    "gn:feature_code":"PPL",
    "gn:name":"Tekoa",
    "gn:population":0,
    "gn:timezone":"Asia/Hebron",
    "iso:country":"PS",
    "name:rus_x_preferred":[
        "\u0422\u0435\u043a\u043e\u0430"
    ],
    "name:und_x_variant":[
        "Tequa",
        "Taqu'",
        "Tequoa"
    ],
    "wof:name":"Tekoa",
    "wof:placetype":"locality"
},
  "geometry": {"coordinates":[35.21496,31.63701],"type":"Point"}
}