{
  "type": "Feature",
  "properties": {
    "gn:country":"PS",
    "gn:fcode":"PPL",
    "gn:population":4917,
    "iso:country":"PS",
    "name:ara_x_preferred":[
        "\u0627\u0644\u0632\u0627\u0648\u064a\u0629"
    ],
    "name:cat_x_preferred":[
        "Zawiya"
    ],
    "name:eng_x_preferred":[
        "Zawiya"
    ],
    "name:heb_x_preferred":[
        "\u05d6\u05d0\u05d5\u05d5\u05d9\u05d4"
    ],
    "name:nld_x_preferred":[
        "Zawiya"
    ],
    "name:nno_x_preferred":[
        "Az-Zawiya"
    ],
    "name:pol_x_preferred":[
        "Az-Zawija"
    ],
    "name:und_x_variant":[
        "Z\u0101wiyah"
    ],
    "qs_pg:aaroncc":"PS",
    "qs_pg:gn_country":"PS",
    "qs_pg:gn_fcode":"PPL",
    "qs_pg:gn_pop":4917,
    "qs_pg:name":"Az Z\u0101wiyah",
    "qs_pg:photos_9r":0,
    "qs_pg:photos_sr":0,
    "qs_pg:pop_sr":4,
    "qs_pg:qs_pg_placetype":"locality",
    "wof:name":"Az Z\u0101wiyah",
    "wof:placetype":"locality",
    "wof:population":4917
},
  "geometry": {"coordinates":[35.03982,32.09627],"type":"Point"}
}