{
  "type": "Feature",
  "properties": {
    "gn:country":"PS",
    "gn:fcode":"PPL",
    "gn:population":3761,
    "iso:country":"PS",
    "name:ara_x_preferred":[
        "\u0642\u0631\u0627\u0648\u0629 \u0628\u0646\u064a \u062d\u0633\u0627\u0646"
    ],
    "name:cat_x_preferred":[
        "Qarawat Bani Hassan"
    ],
    "name:eng_x_preferred":[
        "Qarawat Bani Hassan"
    ],
    "name:heb_x_preferred":[
        "\u05e7\u05e8\u05d0\u05d5\u05d5\u05ea \u05d1\u05e0\u05d9 \u05d7\u05e1\u05df"
    ],
    "name:nld_x_preferred":[
        "Qarawat Bani Hassan"
    ],
    "name:nno_x_preferred":[
        "Qarawat Bani Hassan"
    ],
    "qs_pg:aaroncc":"PS",
    "qs_pg:gn_country":"PS",
    "qs_pg:gn_fcode":"PPL",
    "qs_pg:gn_pop":3761,
    "qs_pg:name":"Qar\u0101wat Ban\u012b \u1e28asan",
    "qs_pg:photos_9r":0,
    "qs_pg:photos_sr":0,
    "qs_pg:pop_sr":4,
    "qs_pg:qs_pg_placetype":"locality",
    "wof:name":"Qar\u0101wat Ban\u012b \u1e28asan",
    "wof:placetype":"locality",
    "wof:population":3761
},
  "geometry": {"coordinates":[35.10061,32.12568],"type":"Point"}
}