{
  "type": "Feature",
  "properties": {
    "gn:admin1_code":"WE",
    "gn:admin2_code":"7870653",
    "gn:asciiname":"Yitav",
    "gn:country_code":"PS",
    "gn:dem":-105,
    "gn:feature_class":"P",
    "gn:feature_code":"STLMT",
    "gn:name":"Yitav",
    "gn:population":0,
    "gn:timezone":"Asia/Hebron",
    "iso:country":"PS",
    "name:ces_x_preferred":[
        "Jitav"
    ],
    "name:heb_x_preferred":[
        "\u05d9\u05d9\u05d8\"\u05d1"
    ],
    "name:nno_x_preferred":[
        "Yitav"
    ],
    "name:pol_x_preferred":[
        "Jitaw"
    ],
    "name:yid_x_preferred":[
        "\u05d9\u05d9\u05d8\"\u05d1"
    ],
    "wof:name":"Yitav",
    "wof:placetype":"locality"
},
  "geometry": {"coordinates":[35.41667,31.95],"type":"Point"}
}