{
  "type": "Feature",
  "properties": {
    "gn:admin1_code":"WE",
    "gn:asciiname":"Mattityahu",
    "gn:cc2":"PS",
    "gn:country_code":"PS",
    "gn:dem":257,
    "gn:feature_class":"P",
    "gn:feature_code":"STLMT",
    "gn:name":"Mattityahu",
    "gn:population":0,
    "gn:timezone":"Asia/Hebron",
    "iso:country":"PS",
    "name:ces_x_preferred":[
        "Matitjahu"
    ],
    "name:heb_x_preferred":[
        "\u05de\u05ea\u05ea\u05d9\u05d4\u05d5"
    ],
    "name:pol_x_preferred":[
        "Mattitjahu"
    ],
    "name:und_x_variant":[
        "Mattiyahu",
        "Mattityahu"
    ],
    "wof:name":"Mattityahu",
    "wof:placetype":"locality"
},
  "geometry": {"coordinates":[35.01667,31.91667],"type":"Point"}
}