{
  "type": "Feature",
  "properties": {
    "gn:gn_country":"PS",
    "gn:gn_fcode":"PPL",
    "gn:gn_pop":131,
    "gn:population":131,
    "iso:country":"PS",
    "name:ara_x_preferred":[
        "\u062e\u0631\u0628\u0629 \u062d\u0645\u0635\u0629"
    ],
    "name:unk_x_variant":[
        "Khirbat el \u1e24um\u1e63a"
    ],
    "qs_pg:aaroncc":"PS",
    "qs_pg:gn_country":"PS",
    "qs_pg:gn_fcode":"PPL",
    "qs_pg:gn_pop":131,
    "qs_pg:name":"Khirbat \u1e28um\u015fah",
    "qs_pg:photos_9r":0,
    "qs_pg:photos_sr":0,
    "qs_pg:pop_sr":1,
    "qs_pg:qs_pg_placetype":"locality",
    "wof:name":"Khirbat \u1e28um\u015fah",
    "wof:placetype":"locality",
    "wof:population":131
},
  "geometry": {"coordinates":[35.49117,32.2345],"type":"Point"}
}