{
  "type": "Feature",
  "properties": {
    "gn:gn_country":"PS",
    "gn:gn_fcode":"PPL",
    "gn:gn_pop":3077,
    "gn:population":3077,
    "iso:country":"PS",
    "name:ara_x_preferred":[
        "\u0639\u0628\u0648\u064a\u0646"
    ],
    "name:eng_x_preferred":[
        "Abwein"
    ],
    "name:fas_x_preferred":[
        "\u0627\u0628\u0648\u06cc\u0646"
    ],
    "name:heb_x_preferred":[
        "\u05e2\u05d1\u05d5\u05d9\u05df"
    ],
    "name:nld_x_preferred":[
        "Abwein"
    ],
    "name:nno_x_preferred":[
        "Abwein"
    ],
    "name:unk_x_variant":[
        "\u2018Ibwein"
    ],
    "qs_pg:aaroncc":"PS",
    "qs_pg:gn_country":"PS",
    "qs_pg:gn_fcode":"PPL",
    "qs_pg:gn_pop":3077,
    "qs_pg:name":"\u2018Ibwayn",
    "qs_pg:photos_9r":0,
    "qs_pg:photos_sr":0,
    "qs_pg:pop_sr":4,
    "qs_pg:qs_pg_placetype":"locality",
    "wof:name":"\u2018Ibwayn",
    "wof:placetype":"locality",
    "wof:population":3077
},
  "geometry": {"coordinates":[35.19992,32.03144],"type":"Point"}
}