{
  "type": "Feature",
  "properties": {
    "gn:country":"PS",
    "gn:fcode":"PPL",
    "gn:population":8535,
    "iso:country":"PS",
    "name:und_x_variant":[
        "Beita al Fauqa"
    ],
    "qs_pg:aaroncc":"PS",
    "qs_pg:gn_country":"PS",
    "qs_pg:gn_fcode":"PPL",
    "qs_pg:gn_pop":8535,
    "qs_pg:name":"Bayt\u0101 al Fawq\u0101",
    "qs_pg:photos_9r":0,
    "qs_pg:photos_sr":0,
    "qs_pg:pop_sr":5,
    "qs_pg:qs_pg_placetype":"locality",
    "wof:name":"Bayt\u0101 al Fawq\u0101",
    "wof:placetype":"locality",
    "wof:population":8535
},
  "geometry": {"coordinates":[35.28774,32.1426],"type":"Point"}
}