{
  "type": "Feature",
  "properties": {
    "gn:country":"PS",
    "gn:fcode":"PPL",
    "gn:population":704,
    "iso:country":"PS",
    "name:ara_x_preferred":[
        "\u0648\u0627\u062f\u064a \u0627\u0644\u0634\u0627\u062c\u0646\u0629"
    ],
    "qs_pg:aaroncc":"PS",
    "qs_pg:gn_country":"PS",
    "qs_pg:gn_fcode":"PPL",
    "qs_pg:gn_pop":704,
    "qs_pg:name":"W\u0101d\u012b ash Sh\u0101jinah",
    "qs_pg:photos_9r":0,
    "qs_pg:photos_sr":0,
    "qs_pg:pop_sr":2,
    "qs_pg:qs_pg_placetype":"locality",
    "wof:name":"W\u0101d\u012b ash Sh\u0101jinah",
    "wof:placetype":"locality",
    "wof:population":704
},
  "geometry": {"coordinates":[35.03151,31.47057],"type":"Point"}
}