{
  "type": "Feature",
  "properties": {
    "gn:country":"PS",
    "gn:fcode":"PPL",
    "gn:population":2823,
    "iso:country":"PS",
    "name:ara_x_preferred":[
        "\u0633\u0628\u0633\u0637\u064a\u0629"
    ],
    "name:bel_x_preferred":[
        "\u0421\u0435\u0431\u0430\u0441\u0442\u044b\u044f"
    ],
    "name:cat_x_preferred":[
        "Sebastia"
    ],
    "name:deu_x_preferred":[
        "Sebastia"
    ],
    "name:eng_x_preferred":[
        "Sebastia"
    ],
    "name:fra_x_preferred":[
        "Sebastia"
    ],
    "name:heb_x_preferred":[
        "\u05e1\u05d1\u05e1\u05d8\u05d9\u05d4"
    ],
    "name:hrv_x_preferred":[
        "Samarija"
    ],
    "name:jpn_x_preferred":[
        "\u30b5\u30d0\u30b9\u30c6\u30a3\u30fc\u30e4"
    ],
    "name:nld_x_preferred":[
        "Sebastia"
    ],
    "name:nno_x_preferred":[
        "Sebastia i Nablus"
    ],
    "name:por_x_preferred":[
        "Sebastia"
    ],
    "name:ron_x_preferred":[
        "Sebastia"
    ],
    "name:spa_x_preferred":[
        "Sebastia"
    ],
    "name:und_x_variant":[
        "Shomron"
    ],
    "qs_pg:aaroncc":"PS",
    "qs_pg:gn_country":"PS",
    "qs_pg:gn_fcode":"PPL",
    "qs_pg:gn_pop":2823,
    "qs_pg:name":"Sabas\u0163\u012byah",
    "qs_pg:photos_9r":0,
    "qs_pg:photos_sr":0,
    "qs_pg:pop_sr":4,
    "qs_pg:qs_pg_placetype":"locality",
    "wof:name":"Sabas\u0163\u012byah",
    "wof:placetype":"locality",
    "wof:population":2823
},
  "geometry": {"coordinates":[35.19873,32.27562],"type":"Point"}
}