{
  "type": "Feature",
  "properties": {
    "iso:country":"PS",
    "qs_pg:aaroncc":"PS",
    "qs_pg:name":"Sheikh Jarakh",
    "qs_pg:name_adm0":"Palestine",
    "qs_pg:name_adm1":"West Bank",
    "qs_pg:photos":46,
    "qs_pg:photos_1k":9,
    "qs_pg:photos_9k":1,
    "qs_pg:photos_9r":2,
    "qs_pg:photos_all":46,
    "qs_pg:photos_sr":2,
    "qs_pg:pop_sr":0,
    "qs_pg:qs_pg_placetype":"neighbourhood",
    "qs_pg:qs_pg_placetype_gp":"Suburb",
    "qs_pg:woe_adm0":28289408,
    "woe:adm0_id":28289408,
    "woe:name_adm0":"Palestine",
    "woe:name_adm1":"West Bank",
    "woe:placetype":"Suburb",
    "wof:name":"Sheikh Jarakh",
    "wof:placetype":"neighbourhood"
},
  "geometry": {"coordinates":[35.231523,31.795424],"type":"Point"}
}