{
  "type": "Feature",
  "properties": {
    "gn:gn_country":"PS",
    "gn:gn_fcode":"PPL",
    "gn:gn_pop":305,
    "gn:population":305,
    "iso:country":"PS",
    "name:ara_x_preferred":[
        "\u0627\u0644\u0646\u0628\u064a \u0645\u0648\u0633\u0649"
    ],
    "qs_pg:aaroncc":"PS",
    "qs_pg:gn_country":"PS",
    "qs_pg:gn_fcode":"PPL",
    "qs_pg:gn_pop":305,
    "qs_pg:name":"An Nab\u012b M\u016bs\u00e1",
    "qs_pg:photos_9r":0,
    "qs_pg:photos_sr":0,
    "qs_pg:pop_sr":2,
    "qs_pg:qs_pg_placetype":"locality",
    "wof:name":"An Nab\u012b M\u016bs\u00e1",
    "wof:placetype":"locality",
    "wof:population":305
},
  "geometry": {"coordinates":[35.4318,31.78648],"type":"Point"}
}