{
  "type": "Feature",
  "properties": {
    "gn:admin1_code":"00",
    "gn:asciiname":"Al `Udaysah",
    "gn:country_code":"PS",
    "gn:dem":985,
    "gn:feature_class":"P",
    "gn:feature_code":"PPL",
    "gn:name":"Al \u2018Udaysah",
    "gn:population":0,
    "gn:timezone":"Asia/Hebron",
    "iso:country":"PS",
    "name:ara_x_preferred":[
        "\u0627\u0644\u0639\u062f\u064a\u0633\u0629"
    ],
    "name:nno_x_preferred":[
        "Al-Uddeisa"
    ],
    "name:und_x_variant":[
        "Al \u2018Udaysah",
        "Khirbat al \u2018Uddeisa",
        "Khirbat al \u2018Udaysah"
    ],
    "wof:name":"Al `Udaysah",
    "wof:placetype":"locality"
},
  "geometry": {"coordinates":[35.13995999999999,31.54796],"type":"Point"}
}