{
  "type": "Feature",
  "properties": {
    "gn:country":"PS",
    "gn:fcode":"PPL",
    "gn:population":713,
    "iso:country":"PS",
    "name:ara_x_preferred":[
        "\u0639\u0632\u0628\u0629 \u0633\u0644\u0645\u0627\u0646"
    ],
    "qs_pg:aaroncc":"PS",
    "qs_pg:gn_country":"PS",
    "qs_pg:gn_fcode":"PPL",
    "qs_pg:gn_pop":713,
    "qs_pg:name":"\u2018Izbat Salm\u0101n",
    "qs_pg:photos_9r":0,
    "qs_pg:photos_sr":0,
    "qs_pg:pop_sr":2,
    "qs_pg:qs_pg_placetype":"locality",
    "wof:name":"\u2018Izbat Salm\u0101n",
    "wof:placetype":"locality",
    "wof:population":713
},
  "geometry": {"coordinates":[34.99829,32.14222],"type":"Point"}
}