{
  "type": "Feature",
  "properties": {
    "gn:gn_country":"PS",
    "gn:gn_fcode":"PPL",
    "gn:gn_pop":676,
    "gn:population":676,
    "iso:country":"PS",
    "name:ara_x_preferred":[
        "\u0645\u0631\u0627\u062d \u0645\u0639\u0644\u0627"
    ],
    "qs_pg:aaroncc":"PS",
    "qs_pg:gn_country":"PS",
    "qs_pg:gn_fcode":"PPL",
    "qs_pg:gn_pop":676,
    "qs_pg:name":"Mar\u0101\u1e29 Ma\u2018all\u0101",
    "qs_pg:photos_9r":0,
    "qs_pg:photos_sr":0,
    "qs_pg:pop_sr":2,
    "qs_pg:qs_pg_placetype":"locality",
    "wof:name":"Mar\u0101\u1e29 Ma\u2018all\u0101",
    "wof:placetype":"locality",
    "wof:population":676
},
  "geometry": {"coordinates":[35.17478,31.64925],"type":"Point"}
}