{
  "type": "Feature",
  "properties": {
    "gn:gn_country":"PS",
    "gn:gn_fcode":"PPL",
    "gn:gn_pop":1919,
    "gn:population":1919,
    "iso:country":"PS",
    "name:ara_x_preferred":[
        "\u0625\u0643\u062a\u0627\u0628\u0629"
    ],
    "name:dut_x_preferred":[
        "Iktaba"
    ],
    "name:eng_x_preferred":[
        "Iktaba"
    ],
    "name:heb_x_preferred":[
        "\u05d0\u05d9\u05db\u05ea\u05d0\u05d1\u05d0"
    ],
    "name:nno_x_preferred":[
        "Iktaba"
    ],
    "name:unk_x_variant":[
        "Iktaba"
    ],
    "qs_pg:aaroncc":"PS",
    "qs_pg:gn_country":"PS",
    "qs_pg:gn_fcode":"PPL",
    "qs_pg:gn_pop":1919,
    "qs_pg:name":"Ikt\u0101bah",
    "qs_pg:photos_9r":0,
    "qs_pg:photos_sr":0,
    "qs_pg:pop_sr":3,
    "qs_pg:qs_pg_placetype":"locality",
    "wof:name":"Ikt\u0101bah",
    "wof:placetype":"locality",
    "wof:population":1919
},
  "geometry": {"coordinates":[35.05262,32.3266],"type":"Point"}
}