{
  "type": "Feature",
  "properties": {
    "gn:country":"PS",
    "gn:fcode":"PPL",
    "gn:population":6681,
    "iso:country":"PS",
    "name:ara_x_preferred":[
        "\u2018Ill\u0101r"
    ],
    "name:ara_x_variant":[
        "\u0639\u0644\u0627\u0631"
    ],
    "qs_pg:aaroncc":"PS",
    "qs_pg:gn_country":"PS",
    "qs_pg:gn_fcode":"PPL",
    "qs_pg:gn_pop":6681,
    "qs_pg:name":"\u2018Ill\u0101r",
    "qs_pg:photos_9r":0,
    "qs_pg:photos_sr":0,
    "qs_pg:pop_sr":5,
    "qs_pg:qs_pg_placetype":"locality",
    "wof:name":"\u2018Ill\u0101r",
    "wof:placetype":"locality",
    "wof:population":6681
},
  "geometry": {"coordinates":[35.10708,32.37024],"type":"Point"}
}