{
  "type": "Feature",
  "properties": {
    "gn:admin1_code":"WE",
    "gn:admin2_code":"7828733",
    "gn:asciiname":"Jalamat as Siyar",
    "gn:country_code":"PS",
    "gn:dem":239,
    "gn:feature_class":"P",
    "gn:feature_code":"PPL",
    "gn:name":"Jalamat as Siy\u0101r",
    "gn:population":0,
    "gn:timezone":"Asia/Hebron",
    "iso:country":"PS",
    "name:und_x_variant":[
        "Jalam\u0101t e\u1e63 \u1e62iyar",
        "Jalamat as Siy\u0101r"
    ],
    "wof:name":"Jalamat as Siyar",
    "wof:placetype":"locality"
},
  "geometry": {"coordinates":[35.29879000000001,32.44329],"type":"Point"}
}