{
  "type": "Feature",
  "properties": {
    "gn:gn_country":"PS",
    "gn:gn_fcode":"PPL",
    "gn:gn_pop":1064,
    "gn:population":1064,
    "iso:country":"PS",
    "name:ara_x_preferred":[
        "\u0627\u0644\u0641\u0635\u0627\u064a\u0644"
    ],
    "name:unk_x_variant":[
        "Paza\u2019el"
    ],
    "qs_pg:aaroncc":"PS",
    "qs_pg:gn_country":"PS",
    "qs_pg:gn_fcode":"PPL",
    "qs_pg:gn_pop":1064,
    "qs_pg:name":"Al Fa\u015f\u0101yil",
    "qs_pg:photos_9r":0,
    "qs_pg:photos_sr":0,
    "qs_pg:pop_sr":3,
    "qs_pg:qs_pg_placetype":"locality",
    "wof:name":"Al Fa\u015f\u0101yil",
    "wof:placetype":"locality",
    "wof:population":1064
},
  "geometry": {"coordinates":[35.44351,32.02509],"type":"Point"}
}