{
  "type": "Feature",
  "properties": {
    "gn:gn_country":"PS",
    "gn:gn_fcode":"PPL",
    "gn:gn_pop":1916,
    "gn:population":1916,
    "iso:country":"PS",
    "name:ara_x_preferred":[
        "\u062f\u064a\u0631 \u0642\u062f\u064a\u0633"
    ],
    "name:eng_x_preferred":[
        "Deir Qaddis"
    ],
    "name:heb_x_preferred":[
        "\u05d3\u05d9\u05e8 \u05e7\u05d3\u05d9\u05e1"
    ],
    "name:nld_x_preferred":[
        "Deir Qaddis"
    ],
    "name:nno_x_preferred":[
        "Deir Qaddis"
    ],
    "name:unk_x_variant":[
        "Deir Qaddis"
    ],
    "qs_pg:aaroncc":"PS",
    "qs_pg:gn_country":"PS",
    "qs_pg:gn_fcode":"PPL",
    "qs_pg:gn_pop":1916,
    "qs_pg:name":"Dayr Qidd\u012bs",
    "qs_pg:photos_9r":0,
    "qs_pg:photos_sr":0,
    "qs_pg:pop_sr":3,
    "qs_pg:qs_pg_placetype":"locality",
    "wof:name":"Dayr Qidd\u012bs",
    "wof:placetype":"locality",
    "wof:population":1916
},
  "geometry": {"coordinates":[35.04437,31.94862],"type":"Point"}
}