{
  "type": "Feature",
  "properties": {
    "gn:admin1_code":"WE",
    "gn:asciiname":"Allon",
    "gn:country_code":"PS",
    "gn:dem":211,
    "gn:feature_class":"P",
    "gn:feature_code":"STLMT",
    "gn:name":"Allon",
    "gn:population":0,
    "gn:timezone":"Asia/Hebron",
    "iso:country":"PS",
    "name:pol_x_preferred":[
        "Allon"
    ],
    "wof:name":"Allon",
    "wof:placetype":"locality"
},
  "geometry": {"coordinates":[35.35,31.81667],"type":"Point"}
}