{
  "type": "Feature",
  "properties": {
    "gn:country":"PS",
    "gn:fcode":"PPL",
    "gn:population":1855,
    "iso:country":"PS",
    "name:ara_x_preferred":[
        "\u0632\u0648\u0627\u062a\u0627"
    ],
    "name:arz_x_preferred":[
        "\u0632\u0648\u0627\u062a\u0627"
    ],
    "name:cat_x_preferred":[
        "Zawata"
    ],
    "name:ceb_x_preferred":[
        "Zaw\u0101t\u0101"
    ],
    "name:eng_x_preferred":[
        "Zawata"
    ],
    "name:fas_x_preferred":[
        "\u0632\u0648\u0627\u062a\u0627"
    ],
    "name:heb_x_preferred":[
        "\u05d6\u05d0\u05d5\u05d5\u05d0\u05ea\u05d0"
    ],
    "name:nld_x_preferred":[
        "Zawata"
    ],
    "qs_pg:aaroncc":"PS",
    "qs_pg:gn_country":"PS",
    "qs_pg:gn_fcode":"PPL",
    "qs_pg:gn_pop":1855,
    "qs_pg:name":"Zaw\u0101t\u0101",
    "qs_pg:photos_9r":0,
    "qs_pg:photos_sr":0,
    "qs_pg:pop_sr":3,
    "qs_pg:qs_pg_placetype":"locality",
    "wof:name":"Zaw\u0101t\u0101",
    "wof:placetype":"locality",
    "wof:population":1855
},
  "geometry": {"coordinates":[35.2265,32.2461],"type":"Point"}
}