{
  "type": "Feature",
  "properties": {
    "gn:admin1_code":"WE",
    "gn:admin2_code":"7870658",
    "gn:asciiname":"al-Kum",
    "gn:country_code":"PS",
    "gn:dem":432,
    "gn:feature_class":"P",
    "gn:feature_code":"PPL",
    "gn:name":"al-Kum",
    "gn:population":2568,
    "gn:timezone":"Asia/Hebron",
    "iso:country":"PS",
    "name:ara_x_preferred":[
        "\u0627\u0644\u0643\u0648\u0645"
    ],
    "name:cat_x_preferred":[
        "Beit Maqdum"
    ],
    "name:ceb_x_preferred":[
        "Al-Kum"
    ],
    "name:fas_x_preferred":[
        "\u0627\u0644-\u06a9\u0627\u0645"
    ],
    "name:heb_x_preferred":[
        "\u05d0\u05dc-\u05db\u05d5\u05dd"
    ],
    "name:nno_x_preferred":[
        "Al-Kum"
    ],
    "name:und_x_variant":[
        "Alkoum"
    ],
    "wof:name":"al-Kum",
    "wof:placetype":"locality",
    "wof:population":2568
},
  "geometry": {"coordinates":[34.96064000000001,31.53123],"type":"Point"}
}