{
  "type": "Feature",
  "properties": {
    "gn:admin1_code":"WE",
    "gn:admin2_code":"7870658",
    "gn:asciiname":"al-Kum",
    "gn:country_code":"PS",
    "gn:dem":432,
    "gn:feature_class":"P",
    "gn:feature_code":"PPL",
    "gn:name":"al-Kum",
    "gn:population":2568,
    "gn:timezone":"Asia/Hebron",
    "iso:country":"PS",
    "name:und_x_variant":[
        "Alkoum"
    ],
    "wof:name":"al-Kum",
    "wof:placetype":"locality",
    "wof:population":2568
},
  "geometry": {"coordinates":[34.96064000000001,31.53123],"type":"Point"}
}