{
  "type": "Feature",
  "properties": {
    "gn:admin1_code":"WE",
    "gn:asciiname":"Khirbat Bayt Nasib al Gharbiyah",
    "gn:country_code":"PS",
    "gn:dem":558,
    "gn:feature_class":"P",
    "gn:feature_code":"PPL",
    "gn:name":"Khirbat Bayt Na\u015f\u012bb al Gharb\u012byah",
    "gn:population":0,
    "gn:timezone":"Asia/Hebron",
    "iso:country":"PS",
    "name:und_x_variant":[
        "Khirbat Beit Na\u1e63\u012bb el Gharbiya",
        "Khirbat Bayt Na\u015f\u012bb al Gharb\u012byah"
    ],
    "wof:name":"Khirbat Bayt Nasib al Gharbiyah",
    "wof:placetype":"locality"
},
  "geometry": {"coordinates":[35.02503,31.59164],"type":"Point"}
}