{
  "type": "Feature",
  "properties": {
    "gn:gn_country":"PS",
    "gn:gn_fcode":"PPL",
    "gn:gn_pop":1433,
    "gn:population":1433,
    "iso:country":"PS",
    "name:ara_x_preferred":[
        "\u0627\u0644\u0637\u064a\u0628\u0629"
    ],
    "name:unk_x_variant":[
        "\u1e6caiyiba"
    ],
    "qs_pg:aaroncc":"PS",
    "qs_pg:gn_country":"PS",
    "qs_pg:gn_fcode":"PPL",
    "qs_pg:gn_pop":1433,
    "qs_pg:name":"A\u0163 \u0162aybah",
    "qs_pg:photos_9r":0,
    "qs_pg:photos_sr":0,
    "qs_pg:pop_sr":3,
    "qs_pg:qs_pg_placetype":"locality",
    "wof:name":"A\u0163 \u0162aybah",
    "wof:placetype":"locality",
    "wof:population":1433
},
  "geometry": {"coordinates":[35.2998,31.95388],"type":"Point"}
}