{
  "type": "Feature",
  "properties": {
    "gn:admin1_code":"00",
    "gn:asciiname":"Furush Bayt Dajan",
    "gn:country_code":"PS",
    "gn:dem":-163,
    "gn:feature_class":"P",
    "gn:feature_code":"PPL",
    "gn:name":"Fur\u016bsh Bayt Dajan",
    "gn:population":0,
    "gn:timezone":"Asia/Hebron",
    "iso:country":"PS",
    "name:ara_x_preferred":[
        "\u0641\u0631\u0648\u0634 \u0628\u064a\u062a \u062f\u062c\u0646"
    ],
    "name:und_x_variant":[
        "Fur\u016bsh Bayt Dajan"
    ],
    "wof:name":"Furush Bayt Dajan",
    "wof:placetype":"locality"
},
  "geometry": {"coordinates":[35.4568,32.18556],"type":"Point"}
}