{
  "type": "Feature",
  "properties": {
    "gn:admin1_code":"00",
    "gn:asciiname":"Dayr al Qilt",
    "gn:country_code":"PS",
    "gn:dem":-57,
    "gn:feature_class":"P",
    "gn:feature_code":"PPL",
    "gn:name":"Dayr al Qil\u0163",
    "gn:population":0,
    "gn:timezone":"Asia/Hebron",
    "iso:country":"PS",
    "name:ara_x_preferred":[
        "\u062f\u064a\u0631 \u0627\u0644\u0642\u0644\u0637"
    ],
    "name:und_x_variant":[
        "Dayr al Qil\u0163"
    ],
    "wof:name":"Dayr al Qilt",
    "wof:placetype":"locality"
},
  "geometry": {"coordinates":[35.40957,31.84144],"type":"Point"}
}