{
  "type": "Feature",
  "properties": {
    "gn:gn_country":"PS",
    "gn:gn_fcode":"PPL",
    "gn:gn_pop":1932,
    "gn:population":1932,
    "iso:country":"PS",
    "name:ara_x_preferred":[
        "\u0627\u0644\u0634\u064a\u062e \u0633\u0639\u062f"
    ],
    "name:eng_x_preferred":[
        "Ash-Sheikh Sa'd"
    ],
    "name:fas_x_preferred":[
        "\u062e\u0631\u0628\u0629 \u0627\u0644\u0634\u06cc\u062e \u0633\u0639\u062f"
    ],
    "name:heb_x_preferred":[
        "\u05e9\u05d9\u05d9\u05d7' \u05e1\u05e2\u05d3"
    ],
    "name:nld_x_preferred":[
        "Ash-Sheikh Sa'd"
    ],
    "name:unk_x_variant":[
        "Khirbat esh Sheikh Sa\u2018ad"
    ],
    "qs_pg:aaroncc":"PS",
    "qs_pg:gn_country":"PS",
    "qs_pg:gn_fcode":"PPL",
    "qs_pg:gn_pop":1932,
    "qs_pg:name":"Ash Shaykh Sa\u2018d",
    "qs_pg:photos_9r":0,
    "qs_pg:photos_sr":0,
    "qs_pg:pop_sr":3,
    "qs_pg:qs_pg_placetype":"locality",
    "wof:name":"Ash Shaykh Sa\u2018d",
    "wof:placetype":"locality",
    "wof:population":1932
},
  "geometry": {"coordinates":[35.25742,31.73721],"type":"Point"}
}