{
  "type": "Feature",
  "properties": {
    "gn:gn_country":"PS",
    "gn:gn_fcode":"PPL",
    "gn:gn_pop":2323,
    "gn:population":2323,
    "iso:country":"PS",
    "name:ara_x_preferred":[
        "\u062a\u064a\u0627\u0633\u064a\u0631"
    ],
    "name:cat_x_preferred":[
        "Tayasir"
    ],
    "name:ceb_x_preferred":[
        "Tay\u0101s\u012br"
    ],
    "name:eng_x_preferred":[
        "Tayasir"
    ],
    "name:heb_x_preferred":[
        "\u05ea\u05d9\u05d0\u05e1\u05d9\u05e8"
    ],
    "name:nld_x_preferred":[
        "Tayasir"
    ],
    "name:nno_x_preferred":[
        "Tayasir"
    ],
    "name:pol_x_preferred":[
        "Tajasir"
    ],
    "name:unk_x_variant":[
        "Tayaseer"
    ],
    "qs_pg:aaroncc":"PS",
    "qs_pg:gn_country":"PS",
    "qs_pg:gn_fcode":"PPL",
    "qs_pg:gn_pop":2323,
    "qs_pg:name":"Tay\u0101s\u012br",
    "qs_pg:photos_9r":0,
    "qs_pg:photos_sr":0,
    "qs_pg:pop_sr":4,
    "qs_pg:qs_pg_placetype":"locality",
    "wof:name":"Tay\u0101s\u012br",
    "wof:placetype":"locality",
    "wof:population":2323
},
  "geometry": {"coordinates":[35.39604,32.34042],"type":"Point"}
}