{
  "type": "Feature",
  "properties": {
    "gn:gn_country":"PS",
    "gn:gn_fcode":"PPL",
    "gn:gn_pop":331,
    "gn:population":331,
    "iso:country":"PS",
    "name:ara_x_preferred":[
        "\u0627\u0644\u0636\u0628\u0639\u0629"
    ],
    "name:unk_x_variant":[
        "Khirbat Magh\u0101rat ed Dab\u2018a"
    ],
    "qs_pg:aaroncc":"PS",
    "qs_pg:gn_country":"PS",
    "qs_pg:gn_fcode":"PPL",
    "qs_pg:gn_pop":331,
    "qs_pg:name":"A\u1e11 \u1e10ab\u2018ah",
    "qs_pg:photos_9r":0,
    "qs_pg:photos_sr":0,
    "qs_pg:pop_sr":2,
    "qs_pg:qs_pg_placetype":"locality",
    "wof:name":"A\u1e11 \u1e10ab\u2018ah",
    "wof:placetype":"locality",
    "wof:population":331
},
  "geometry": {"coordinates":[35.00957,32.15841],"type":"Point"}
}