{
  "type": "Feature",
  "properties": {
    "gn:admin1_code":"WE",
    "gn:asciiname":"Bayt Ghur al-Tahta",
    "gn:country_code":"PS",
    "gn:dem":404,
    "gn:feature_class":"P",
    "gn:feature_code":"PPL",
    "gn:name":"Bayt Ghur al-Tahta",
    "gn:population":0,
    "gn:timezone":"Asia/Hebron",
    "iso:country":"PS",
    "name:und_x_variant":[
        "Beit our Tihta"
    ],
    "wof:name":"Bayt Ghur al-Tahta",
    "wof:placetype":"locality"
},
  "geometry": {"coordinates":[35.08391,31.89543],"type":"Point"}
}