{
  "type": "Feature",
  "properties": {
    "gn:country":"PS",
    "gn:fcode":"PPL",
    "gn:population":1129,
    "iso:country":"PS",
    "name:ara_x_preferred":[
        "\u0643\u0641\u0631 \u0642\u0648\u062f"
    ],
    "name:arz_x_preferred":[
        "\u0643\u0641\u0631 \u0642\u0648\u062f"
    ],
    "name:cat_x_preferred":[
        "Kafr Qud"
    ],
    "name:ceb_x_preferred":[
        "Kafr Q\u016bd"
    ],
    "name:eng_x_preferred":[
        "Kafr Qud"
    ],
    "name:fas_x_preferred":[
        "\u06a9\u0641\u0631 \u0642\u0648\u062f"
    ],
    "name:nld_x_preferred":[
        "Kafr Qud"
    ],
    "qs_pg:aaroncc":"PS",
    "qs_pg:gn_country":"PS",
    "qs_pg:gn_fcode":"PPL",
    "qs_pg:gn_pop":1129,
    "qs_pg:name":"Kafr Q\u016bd",
    "qs_pg:photos_9r":0,
    "qs_pg:photos_sr":0,
    "qs_pg:pop_sr":3,
    "qs_pg:qs_pg_placetype":"locality",
    "wof:name":"Kafr Q\u016bd",
    "wof:placetype":"locality",
    "wof:population":1129
},
  "geometry": {"coordinates":[35.22649,32.45661],"type":"Point"}
}