{
  "type": "Feature",
  "properties": {
    "gn:admin1_code":"WE",
    "gn:admin2_code":"7870653",
    "gn:asciiname":"Netiv HaGedud",
    "gn:country_code":"PS",
    "gn:dem":-98,
    "gn:feature_class":"P",
    "gn:feature_code":"STLMT",
    "gn:name":"Netiv HaGedud",
    "gn:population":0,
    "gn:timezone":"Asia/Hebron",
    "iso:country":"PS",
    "name:ces_x_preferred":[
        "Netiv ha-Gdud"
    ],
    "name:heb_x_preferred":[
        "\u05e0\u05ea\u05d9\u05d1 \u05d4\u05d2\u05d3\u05d5\u05d3"
    ],
    "name:nno_x_preferred":[
        "Netiv HaGdud"
    ],
    "name:pol_x_preferred":[
        "Netiw ha-Gedud"
    ],
    "name:rus_x_preferred":[
        "\u041d\u0435\u0442\u0438\u0432-\u0445\u0430-\u0413\u0434\u0443\u0434"
    ],
    "name:srp_x_preferred":[
        "\u041d\u0435\u0442\u0438\u0432 \u0425\u0430\u0433\u0434\u0443\u0434"
    ],
    "wof:name":"Netiv HaGedud",
    "wof:placetype":"locality"
},
  "geometry": {"coordinates":[35.43333,31.98333],"type":"Point"}
}