{
  "type": "Feature",
  "properties": {
    "iso:country":"PS",
    "name:ces_x_preferred":[
        "Giv'at \u0160apira"
    ],
    "name:eng_x_preferred":[
        "Giv'at Shapira"
    ],
    "name:eng_x_variant":[
        "Givat Shapira"
    ],
    "name:fra_x_preferred":[
        "Givat-Shapira"
    ],
    "name:heb_x_preferred":[
        "\u05d2\u05d1\u05e2\u05ea \u05e9\u05e4\u05d9\u05e8\u05d0"
    ],
    "name:nno_x_preferred":[
        "Givat Shapira"
    ],
    "name:pol_x_preferred":[
        "Givat Shapira"
    ],
    "name:unk_x_variant":[
        "Giv'at Shapira"
    ],
    "qs:gn_local":0,
    "qs:local_max":3093,
    "qs:local_sum":12688,
    "qs:localhoods":16,
    "qs:name":"Giv'at Shapira",
    "qs:name_adm0":"Palestine",
    "qs:name_adm1":"West Bank",
    "qs:name_adm2":"Jerusalem",
    "qs:name_local":"\u0627\u0644\u0642\u062f\u0633 \u0627\u0644\u0634\u0631\u0642\u064a\u0629",
    "qs:photo_max":25,
    "qs:photo_sum":50,
    "qs:placetype":"Suburb",
    "qs:quad_count":5,
    "qs:woe_adm0":28289408,
    "qs:woe_adm1":23424988,
    "qs:woe_adm2":24549736,
    "qs:woe_lau":0,
    "qs:woe_local":56126012,
    "qs:woe_ver":"7.10.0",
    "wd:wordcount":79,
    "wof:lang":[
        "eng"
    ],
    "wof:name":"Giv'at Shapira",
    "wof:placetype":"neighbourhood"
},
  "geometry": {"coordinates":[35.228442,31.80676],"type":"Point"}
}