{
  "type": "Feature",
  "properties": {
    "gn:admin1_code":"WE",
    "gn:asciiname":"Khirbat Bayt Nasib ash Sharqiyah",
    "gn:country_code":"PS",
    "gn:dem":557,
    "gn:feature_class":"P",
    "gn:feature_code":"PPL",
    "gn:name":"Khirbat Bayt Na\u015f\u012bb ash Sharq\u012byah",
    "gn:population":0,
    "gn:timezone":"Asia/Hebron",
    "iso:country":"PS",
    "name:und_x_variant":[
        "Khirbat Beit Na\u1e63\u012bb esh Sharqiya",
        "Khirbat Beit Nasib",
        "Khirbat Bayt Na\u015f\u012bb",
        "Khirbat Bayt Na\u015f\u012bb ash Sharq\u012byah"
    ],
    "wof:name":"Khirbat Bayt Nasib ash Sharqiyah",
    "wof:placetype":"locality"
},
  "geometry": {"coordinates":[35.02457,31.58805],"type":"Point"}
}