{
  "type": "Feature",
  "properties": {
    "gn:gn_country":"PS",
    "gn:gn_fcode":"PPL",
    "gn:gn_pop":16183,
    "gn:population":16183,
    "iso:country":"PS",
    "name:ara_x_preferred":[
        "\u0628\u064a\u062a \u062c\u0627\u0644\u0627"
    ],
    "name:cat_x_preferred":[
        "Beit Jala"
    ],
    "name:ces_x_preferred":[
        "Bajt D\u017eal\u00e1"
    ],
    "name:deu_x_preferred":[
        "Bait Dschala"
    ],
    "name:eng_x_preferred":[
        "Beit Jala"
    ],
    "name:fas_x_preferred":[
        "\u0628\u06cc\u062a \u062c\u0627\u0644\u0627"
    ],
    "name:fin_x_preferred":[
        "Beit Jala"
    ],
    "name:fra_x_preferred":[
        "Beit Jala"
    ],
    "name:heb_x_preferred":[
        "\u05d1\u05d9\u05ea \u05d2'\u05d0\u05dc\u05d0"
    ],
    "name:ita_x_preferred":[
        "Beit Jala"
    ],
    "name:jav_x_preferred":[
        "Beit Jala"
    ],
    "name:nld_x_preferred":[
        "Beit Jala"
    ],
    "name:nno_x_preferred":[
        "Beit Jala"
    ],
    "name:pnb_x_preferred":[
        "\u0628\u06cc\u062a \u062c\u0627\u0644\u06c1"
    ],
    "name:pol_x_preferred":[
        "Bajt D\u017cala"
    ],
    "name:por_x_preferred":[
        "Bet-Jalla"
    ],
    "name:rus_x_preferred":[
        "\u0411\u0435\u0439\u0442-\u0414\u0436\u0430\u043b\u0430"
    ],
    "name:spa_x_preferred":[
        "Beit Jala"
    ],
    "name:ukr_x_preferred":[
        "\u0411\u0435\u0439\u0442-\u0414\u0436\u0430\u043b\u0430"
    ],
    "name:unk_x_variant":[
        "Beit J\u0101l\u0101"
    ],
    "name:urd_x_preferred":[
        "\u0628\u06cc\u062a \u062c\u0627\u0644\u0627"
    ],
    "qs_pg:aaroncc":"PS",
    "qs_pg:gn_country":"PS",
    "qs_pg:gn_fcode":"PPL",
    "qs_pg:gn_pop":16183,
    "qs_pg:name":"Bayt Jala",
    "qs_pg:name_adm0":"Palestine",
    "qs_pg:name_adm1":"West Bank",
    "qs_pg:photos":293,
    "qs_pg:photos_1k":59,
    "qs_pg:photos_9k":1,
    "qs_pg:photos_9r":4,
    "qs_pg:photos_all":293,
    "qs_pg:photos_sr":5,
    "qs_pg:pop_sr":6,
    "qs_pg:qs_pg_placetype":"locality",
    "qs_pg:qs_pg_placetype_gp":"Town",
    "qs_pg:woe_adm0":28289408,
    "woe:adm0_id":28289408,
    "woe:name_adm0":"Palestine",
    "woe:name_adm1":"West Bank",
    "woe:placetype":"Town",
    "wof:name":"Bayt Jala",
    "wof:placetype":"locality",
    "wof:population":16183
},
  "geometry": {"coordinates":[35.18788,31.71545],"type":"Point"}
}