{
  "type": "Feature",
  "properties": {
    "gn:admin1_code":"WE",
    "gn:asciiname":"Al-Ittihad",
    "gn:country_code":"PS",
    "gn:dem":528,
    "gn:feature_class":"P",
    "gn:feature_code":"PPL",
    "gn:name":"Al-Ittihad",
    "gn:population":0,
    "gn:timezone":"Asia/Hebron",
    "iso:country":"PS",
    "name:ita_x_preferred":[
        "Al-Ittihad"
    ],
    "name:zho_x_preferred":[
        "\u4f0a\u8482\u54c8\u5fb7"
    ],
    "wof:name":"Al-Ittihad",
    "wof:placetype":"locality"
},
  "geometry": {"coordinates":[35.10188,31.96676],"type":"Point"}
}