{
  "type": "Feature",
  "properties": {
    "gn:admin1_code":"WE",
    "gn:asciiname":"Al-Ittihad",
    "gn:country_code":"PS",
    "gn:dem":528,
    "gn:feature_class":"P",
    "gn:feature_code":"PPL",
    "gn:name":"Al-Ittihad",
    "gn:population":0,
    "gn:timezone":"Asia/Hebron",
    "iso:country":"PS",
    "name:ara_x_preferred":[
        "\u0627\u0644\u0627\u062a\u062d\u0627\u062f"
    ],
    "name:cat_x_preferred":[
        "Al-Ittihad"
    ],
    "name:ces_x_preferred":[
        "Al-Ittihad"
    ],
    "name:deu_x_preferred":[
        "Al-Ittihad"
    ],
    "name:fas_x_preferred":[
        "\u0627\u0644\u0627\u062a\u062d\u0627\u062f"
    ],
    "name:fra_x_preferred":[
        "Al Ittihad"
    ],
    "name:heb_x_preferred":[
        "\u05d0\u05dc-\u05d0\u05d9\u05ea\u05d9\u05d7\u05d0\u05d3"
    ],
    "name:ind_x_preferred":[
        "Al Ittihad"
    ],
    "name:ita_x_preferred":[
        "Al-Ittihad"
    ],
    "name:jpn_x_preferred":[
        "\u30a2\u30eb\u30fb\u30a4\u30c6\u30cf\u30c9"
    ],
    "name:kor_x_preferred":[
        "\uc54c\uc774\ud2f0\ud558\ub4dc"
    ],
    "name:lit_x_preferred":[
        "Al-Ittihad"
    ],
    "name:nld_x_preferred":[
        "Al-Ittihad"
    ],
    "name:por_x_preferred":[
        "Al-Ittihad"
    ],
    "name:rus_x_preferred":[
        "\u0410\u043b\u044c-\u0418\u0442\u0442\u0438\u0445\u0430\u0434"
    ],
    "name:spa_x_preferred":[
        "Al-Ittihad"
    ],
    "name:ukr_x_preferred":[
        "\u0410\u043b\u044c-\u0406\u0442\u0442\u0456\u0445\u0430\u0434"
    ],
    "name:zho_x_preferred":[
        "\u4f0a\u8482\u54c8\u5fb7"
    ],
    "wof:name":"Al-Ittihad",
    "wof:placetype":"locality"
},
  "geometry": {"coordinates":[35.10188,31.96676],"type":"Point"}
}