{
  "type": "Feature",
  "properties": {
    "gn:admin1_code":"WE",
    "gn:admin2_code":"7870463",
    "gn:asciiname":"Ar Ru`ah",
    "gn:country_code":"PS",
    "gn:dem":628,
    "gn:feature_class":"P",
    "gn:feature_code":"PPL",
    "gn:name":"Ar Ru\u2018\u0101h",
    "gn:population":0,
    "gn:timezone":"Asia/Hebron",
    "iso:country":"PS",
    "name:und_x_variant":[
        "Ar Ru\u2018\u0101t",
        "Er Ru\u2018\u0101t",
        "Ar Ru\u2018\u0101h"
    ],
    "wof:name":"Ar Ru`ah",
    "wof:placetype":"locality"
},
  "geometry": {"coordinates":[35.23053,31.70496],"type":"Point"}
}