{
  "type": "Feature",
  "properties": {
    "gn:country":"PS",
    "gn:fcode":"PPL",
    "gn:population":1972,
    "iso:country":"PS",
    "name:ara_x_preferred":[
        "\u0639\u0631\u0627\u0646\u0629"
    ],
    "name:arz_x_preferred":[
        "\u0639\u0631\u0627\u0646\u0647"
    ],
    "name:cat_x_preferred":[
        "Arranah"
    ],
    "name:ceb_x_preferred":[
        "\u2018Arr\u0101nah"
    ],
    "name:eng_x_preferred":[
        "Arranah"
    ],
    "name:fas_x_preferred":[
        "\u0639\u0631\u0627\u0646\u0647"
    ],
    "name:heb_x_preferred":[
        "\u05e2\u05e8\u05d0\u05e0\u05d4"
    ],
    "name:nld_x_preferred":[
        "Arranah"
    ],
    "name:nno_x_preferred":[
        "Arranah"
    ],
    "name:pol_x_preferred":[
        "Arrana"
    ],
    "name:und_x_variant":[
        "\u2018Arr\u0101na"
    ],
    "qs_pg:aaroncc":"PS",
    "qs_pg:gn_country":"PS",
    "qs_pg:gn_fcode":"PPL",
    "qs_pg:gn_pop":1972,
    "qs_pg:name":"\u2018Arr\u0101nah",
    "qs_pg:photos_9r":0,
    "qs_pg:photos_sr":0,
    "qs_pg:pop_sr":3,
    "qs_pg:qs_pg_placetype":"locality",
    "wof:name":"\u2018Arr\u0101nah",
    "wof:placetype":"locality",
    "wof:population":1972
},
  "geometry": {"coordinates":[35.32271,32.4972],"type":"Point"}
}