{
  "type": "Feature",
  "properties": {
    "gn:country":"PS",
    "gn:fcode":"PPL",
    "gn:population":1641,
    "iso:country":"PS",
    "name:ara_x_preferred":[
        "\u0631\u0627\u0633 \u0643\u0631\u0643\u0631"
    ],
    "name:ara_x_variant":[
        "\u0631\u0623\u0633 \u0643\u0631\u0643\u0631"
    ],
    "name:cat_x_preferred":[
        "Ras Karkar"
    ],
    "name:ceb_x_preferred":[
        "R\u0101s Karkar"
    ],
    "name:eng_x_preferred":[
        "Ras Karkar"
    ],
    "name:heb_x_preferred":[
        "\u05e8\u05d0\u05e1 \u05db\u05e8\u05db\u05e8"
    ],
    "name:nld_x_preferred":[
        "Ras Karkar"
    ],
    "name:nno_x_preferred":[
        "Ras Karkar"
    ],
    "name:pol_x_preferred":[
        "Ras Karkar"
    ],
    "name:und_x_variant":[
        "Ra\u2019s Karkar"
    ],
    "qs_pg:aaroncc":"PS",
    "qs_pg:gn_country":"PS",
    "qs_pg:gn_fcode":"PPL",
    "qs_pg:gn_pop":1641,
    "qs_pg:name":"R\u0101s Karkar",
    "qs_pg:photos_9r":0,
    "qs_pg:photos_sr":0,
    "qs_pg:pop_sr":3,
    "qs_pg:qs_pg_placetype":"locality",
    "wof:name":"R\u0101s Karkar",
    "wof:placetype":"locality",
    "wof:population":1641
},
  "geometry": {"coordinates":[35.10773,31.9424],"type":"Point"}
}