{
  "type": "Feature",
  "properties": {
    "gn:gn_country":"PS",
    "gn:gn_fcode":"PPL",
    "gn:gn_pop":4681,
    "gn:population":4681,
    "iso:country":"PS",
    "name:ara_x_preferred":[
        "\u0627\u0644\u062c\u062f\u064a\u062f\u0629"
    ],
    "name:cat_x_preferred":[
        "Al-Judeida"
    ],
    "name:eng_x_preferred":[
        "Judeida"
    ],
    "name:nld_x_preferred":[
        "Judeida"
    ],
    "name:unk_x_variant":[
        "Judeida"
    ],
    "qs_pg:aaroncc":"PS",
    "qs_pg:gn_country":"PS",
    "qs_pg:gn_fcode":"PPL",
    "qs_pg:gn_pop":4681,
    "qs_pg:name":"Al Judayyidah",
    "qs_pg:photos_9r":0,
    "qs_pg:photos_sr":0,
    "qs_pg:pop_sr":4,
    "qs_pg:qs_pg_placetype":"locality",
    "wof:name":"Al Judayyidah",
    "wof:placetype":"locality",
    "wof:population":4681
},
  "geometry": {"coordinates":[35.30108,32.33541],"type":"Point"}
}