{
  "type": "Feature",
  "properties": {
    "gn:gn_country":"PS",
    "gn:gn_fcode":"PPL",
    "gn:gn_pop":692,
    "gn:population":692,
    "iso:country":"PS",
    "name:ara_x_preferred":[
        "\u0628\u064a\u062a \u0625\u062c\u0632\u0627"
    ],
    "name:dut_x_preferred":[
        "Beit Ijza"
    ],
    "name:eng_x_preferred":[
        "Beit Ijza"
    ],
    "name:per_x_preferred":[
        "\u0628\u06cc\u062a \u0627\u062c\u0632\u0627"
    ],
    "name:unk_x_variant":[
        "Beit Ijza"
    ],
    "qs_pg:aaroncc":"PS",
    "qs_pg:gn_country":"PS",
    "qs_pg:gn_fcode":"PPL",
    "qs_pg:gn_pop":692,
    "qs_pg:name":"Bayt Ijz\u0101",
    "qs_pg:photos_9r":0,
    "qs_pg:photos_sr":0,
    "qs_pg:pop_sr":2,
    "qs_pg:qs_pg_placetype":"locality",
    "wof:name":"Bayt Ijz\u0101",
    "wof:placetype":"locality",
    "wof:population":692
},
  "geometry": {"coordinates":[35.15173,31.84675],"type":"Point"}
}