{
  "type": "Feature",
  "properties": {
    "gn:gn_country":"PS",
    "gn:gn_fcode":"PPL",
    "gn:gn_pop":622,
    "gn:population":622,
    "iso:country":"PS",
    "name:aar_x_preferred":[
        "\u0637\u0631\u0627\u0645\u0629"
    ],
    "name:ara_x_preferred":[
        "\u0637\u0631\u0627\u0645\u0629"
    ],
    "name:dut_x_preferred":[
        "Tarrama"
    ],
    "name:eng_x_preferred":[
        "Tarrama"
    ],
    "name:unk_x_variant":[
        "Khirbat al Tarr\u0101ma"
    ],
    "qs_pg:aaroncc":"PS",
    "qs_pg:gn_country":"PS",
    "qs_pg:gn_fcode":"PPL",
    "qs_pg:gn_pop":622,
    "qs_pg:name":"\u0162arr\u0101mah",
    "qs_pg:photos_9r":0,
    "qs_pg:photos_sr":0,
    "qs_pg:pop_sr":2,
    "qs_pg:qs_pg_placetype":"locality",
    "wof:name":"\u0162arr\u0101mah",
    "wof:placetype":"locality",
    "wof:population":622
},
  "geometry": {"coordinates":[35.03252,31.48081],"type":"Point"}
}