{
  "type": "Feature",
  "properties": {
    "gn:country":"PS",
    "gn:fcode":"PPL",
    "gn:population":3072,
    "iso:country":"PS",
    "name:ara_x_preferred":[
        "\u0641\u0631\u0639\u0648\u0646"
    ],
    "name:arz_x_preferred":[
        "\u0641\u0631\u0639\u0648\u0646"
    ],
    "name:cat_x_preferred":[
        "Far'un"
    ],
    "name:eng_x_preferred":[
        "Far'un"
    ],
    "name:heb_x_preferred":[
        "\u05e4\u05e8\u05e2\u05d5\u05df"
    ],
    "name:nld_x_preferred":[
        "Far'un"
    ],
    "name:nno_x_preferred":[
        "Far'un"
    ],
    "name:pol_x_preferred":[
        "Farun"
    ],
    "name:und_x_variant":[
        "Far\u2018un"
    ],
    "qs_pg:aaroncc":"PS",
    "qs_pg:gn_country":"PS",
    "qs_pg:gn_fcode":"PPL",
    "qs_pg:gn_pop":3072,
    "qs_pg:name":"Far\u2018\u016bn",
    "qs_pg:photos_9r":0,
    "qs_pg:photos_sr":0,
    "qs_pg:pop_sr":4,
    "qs_pg:qs_pg_placetype":"locality",
    "wof:name":"Far\u2018\u016bn",
    "wof:placetype":"locality",
    "wof:population":3072
},
  "geometry": {"coordinates":[35.02326,32.28613],"type":"Point"}
}