{
  "type": "Feature",
  "properties": {
    "gn:gn_country":"PS",
    "gn:gn_fcode":"PPL",
    "gn:gn_pop":1845,
    "gn:population":1845,
    "iso:country":"PS",
    "name:ara_x_preferred":[
        "\u0627\u0644\u0645\u0635\u062f\u0631"
    ],
    "name:cat_x_preferred":[
        "Al-Musaddar"
    ],
    "name:eng_x_preferred":[
        "Al-Musaddar"
    ],
    "name:fas_x_preferred":[
        "\u0627\u0644-\u0645\u0648\u0633\u0627\u062f\u0627\u0631"
    ],
    "name:ind_x_preferred":[
        "Al-Musaddar"
    ],
    "name:nld_x_preferred":[
        "Al-Musaddar"
    ],
    "name:nno_x_preferred":[
        "Al-Musaddar"
    ],
    "name:unk_x_variant":[
        "Al Musaddar"
    ],
    "qs_pg:aaroncc":"PS",
    "qs_pg:gn_country":"PS",
    "qs_pg:gn_fcode":"PPL",
    "qs_pg:gn_pop":1845,
    "qs_pg:name":"Al Mu\u015faddar",
    "qs_pg:photos_9r":0,
    "qs_pg:photos_sr":0,
    "qs_pg:pop_sr":3,
    "qs_pg:qs_pg_placetype":"locality",
    "wof:name":"Al Mu\u015faddar",
    "wof:placetype":"locality",
    "wof:population":1845
},
  "geometry": {"coordinates":[34.37802,31.41052],"type":"Point"}
}