{
  "type": "Feature",
  "properties": {
    "gn:admin1_code":"WE",
    "gn:asciiname":"Ash Shaykh Falih",
    "gn:country_code":"PS",
    "gn:dem":-303,
    "gn:feature_class":"P",
    "gn:feature_code":"PPL",
    "gn:name":"Ash Shaykh F\u0101li\u1e29",
    "gn:population":0,
    "gn:timezone":"Asia/Hebron",
    "iso:country":"PS",
    "name:und_x_variant":[
        "Sheikh Falih",
        "Esh Sheikh Falih",
        "Ash Shaykh F\u0101li\u1e29"
    ],
    "wof:name":"Ash Shaykh Falih",
    "wof:placetype":"locality"
},
  "geometry": {"coordinates":[35.55859,32.28822],"type":"Point"}
}