{
  "type": "Feature",
  "properties": {
    "gn:country":"PS",
    "gn:fcode":"PPL",
    "gn:population":608,
    "iso:country":"PS",
    "name:ara_x_preferred":[
        "Burh\u0101m"
    ],
    "name:ara_x_variant":[
        "\u0628\u0631\u0647\u0627\u0645"
    ],
    "name:cat_x_preferred":[
        "Burham"
    ],
    "name:eng_x_preferred":[
        "Burham"
    ],
    "name:nld_x_preferred":[
        "Burham"
    ],
    "name:nno_x_preferred":[
        "Burham i Ramallah"
    ],
    "name:pol_x_preferred":[
        "Burham"
    ],
    "name:und_x_variant":[
        "Burbam"
    ],
    "qs_pg:aaroncc":"PS",
    "qs_pg:gn_country":"PS",
    "qs_pg:gn_fcode":"PPL",
    "qs_pg:gn_pop":608,
    "qs_pg:name":"Burh\u0101m",
    "qs_pg:photos_9r":0,
    "qs_pg:photos_sr":0,
    "qs_pg:pop_sr":2,
    "qs_pg:qs_pg_placetype":"locality",
    "wof:name":"Burh\u0101m",
    "wof:placetype":"locality",
    "wof:population":608
},
  "geometry": {"coordinates":[35.17412,31.98964],"type":"Point"}
}