{
  "type": "Feature",
  "properties": {
    "gn:admin1_code":"WE",
    "gn:asciiname":"Bayt al-Rush al-Tahta",
    "gn:country_code":"PS",
    "gn:dem":454,
    "gn:feature_class":"P",
    "gn:feature_code":"PPL",
    "gn:name":"Bayt al-Rush al-Tahta",
    "gn:population":0,
    "gn:timezone":"Asia/Hebron",
    "iso:country":"PS",
    "name:und_x_variant":[
        "Beit Rosh Tihta"
    ],
    "wof:name":"Bayt al-Rush al-Tahta",
    "wof:placetype":"locality"
},
  "geometry": {"coordinates":[34.93552,31.46376],"type":"Point"}
}