{
  "type": "Feature",
  "properties": {
    "gn:country":"PS",
    "gn:fcode":"PPL",
    "gn:population":500,
    "iso:country":"PS",
    "name:ara_x_preferred":[
        "Ijnisiny\u0101"
    ],
    "name:ara_x_variant":[
        "\u0625\u062c\u0646\u0633\u0646\u064a\u0627"
    ],
    "name:cat_x_preferred":[
        "Ijnisinya"
    ],
    "name:ceb_x_preferred":[
        "Ijnisiny\u0101"
    ],
    "name:eng_x_preferred":[
        "Ijnisinya"
    ],
    "name:heb_x_preferred":[
        "\u05d0\u05d9\u05d2'\u05e0\u05d9\u05e1\u05d9\u05e0\u05d9\u05d0"
    ],
    "name:nld_x_preferred":[
        "Ijnisinya"
    ],
    "name:nno_x_preferred":[
        "Ijnisinya"
    ],
    "name:pol_x_preferred":[
        "Id\u017cnisinja"
    ],
    "qs_pg:aaroncc":"PS",
    "qs_pg:gn_country":"PS",
    "qs_pg:gn_fcode":"PPL",
    "qs_pg:gn_pop":500,
    "qs_pg:name":"Ijnisiny\u0101",
    "qs_pg:photos_9r":0,
    "qs_pg:photos_sr":0,
    "qs_pg:pop_sr":2,
    "qs_pg:qs_pg_placetype":"locality",
    "wof:name":"Ijnisiny\u0101",
    "wof:placetype":"locality",
    "wof:population":500
},
  "geometry": {"coordinates":[35.21586,32.27332],"type":"Point"}
}