{
  "type": "Feature",
  "properties": {
    "gn:country":"PS",
    "gn:fcode":"PPL",
    "gn:population":2059,
    "iso:country":"PS",
    "name:ara_x_preferred":[
        "\u0627\u0644\u062c\u062f\u064a\u0631\u0629"
    ],
    "name:und_x_variant":[
        "Jud\u012brah"
    ],
    "qs_pg:aaroncc":"PS",
    "qs_pg:gn_country":"PS",
    "qs_pg:gn_fcode":"PPL",
    "qs_pg:gn_pop":2059,
    "qs_pg:name":"Judayrah",
    "qs_pg:name_adm0":"Palestine",
    "qs_pg:name_adm1":"West Bank",
    "qs_pg:photos_9r":0,
    "qs_pg:photos_sr":0,
    "qs_pg:pop_sr":4,
    "qs_pg:qs_pg_placetype":"neighbourhood",
    "qs_pg:qs_pg_placetype_gp":"Suburb",
    "qs_pg:woe_adm0":28289408,
    "woe:adm0_id":28289408,
    "woe:name_adm0":"Palestine",
    "woe:name_adm1":"West Bank",
    "woe:placetype":"Suburb",
    "wof:name":"Judayrah",
    "wof:placetype":"neighbourhood",
    "wof:population":2059
},
  "geometry": {"coordinates":[35.19706,31.85587],"type":"Point"}
}