{
  "type": "Feature",
  "properties": {
    "gn:admin1_code":"WE",
    "gn:admin2_code":"7870653",
    "gn:asciiname":"Khirbat Muqaysimah",
    "gn:country_code":"PS",
    "gn:dem":107,
    "gn:feature_class":"P",
    "gn:feature_code":"PPL",
    "gn:name":"Khirbat Muqaysimah",
    "gn:population":0,
    "gn:timezone":"Asia/Hebron",
    "iso:country":"PS",
    "name:und_x_variant":[
        "Khirbat Muqeisima",
        "Khirbat Muqaysimah"
    ],
    "wof:name":"Khirbat Muqaysimah",
    "wof:placetype":"locality"
},
  "geometry": {"coordinates":[35.4548,32.24269],"type":"Point"}
}