{
  "type": "Feature",
  "properties": {
    "gn:admin1_code":"WE",
    "gn:asciiname":"al-Minya",
    "gn:country_code":"PS",
    "gn:dem":787,
    "gn:feature_class":"P",
    "gn:feature_code":"PPL",
    "gn:name":"al-Minya",
    "gn:population":0,
    "gn:timezone":"Asia/Hebron",
    "iso:country":"PS",
    "wof:name":"al-Minya",
    "wof:placetype":"locality"
},
  "geometry": {"coordinates":[35.21848,31.62042000000001],"type":"Point"}
}