{
  "type": "Feature",
  "properties": {
    "gn:country":"PS",
    "gn:fcode":"PPL",
    "gn:population":4126,
    "iso:country":"PS",
    "name:ara_x_preferred":[
        "\u0628\u0631\u0637\u0639\u0629 \u0627\u0644\u0634\u0631\u0642\u064a\u0629"
    ],
    "name:und_x_variant":[
        "Khirbat Bar\u1e6da\u2018a"
    ],
    "qs_pg:aaroncc":"PS",
    "qs_pg:gn_country":"PS",
    "qs_pg:gn_fcode":"PPL",
    "qs_pg:gn_pop":4126,
    "qs_pg:name":"Bar\u0163a\u2018ah ash Sharq\u012byah",
    "qs_pg:photos_9r":0,
    "qs_pg:photos_sr":0,
    "qs_pg:pop_sr":4,
    "qs_pg:qs_pg_placetype":"locality",
    "wof:name":"Bar\u0163a\u2018ah ash Sharq\u012byah",
    "wof:placetype":"locality",
    "wof:population":4126
},
  "geometry": {"coordinates":[35.0936,32.47304],"type":"Point"}
}