{
  "type": "Feature",
  "properties": {
    "gn:admin1_code":"WE",
    "gn:asciiname":"Brosh",
    "gn:country_code":"PS",
    "gn:dem":-167,
    "gn:feature_class":"P",
    "gn:feature_code":"STLMT",
    "gn:name":"Brosh",
    "gn:population":0,
    "gn:timezone":"Asia/Hebron",
    "iso:country":"PS",
    "wof:name":"Brosh",
    "wof:placetype":"locality"
},
  "geometry": {"coordinates":[35.53333,32.31667],"type":"Point"}
}