{
  "type": "Feature",
  "properties": {
    "gn:admin1_code":"WE",
    "gn:asciiname":"Nur ash Shams",
    "gn:cc2":"PS",
    "gn:country_code":"PS",
    "gn:dem":137,
    "gn:feature_class":"P",
    "gn:feature_code":"PPL",
    "gn:name":"N\u016br ash Shams",
    "gn:population":0,
    "gn:timezone":"Asia/Hebron",
    "iso:country":"PS",
    "name:und_x_variant":[
        "Nur es Shams",
        "Nur esh Shems",
        "N\u016br ash Shams"
    ],
    "wof:name":"Nur ash Shams",
    "wof:placetype":"locality"
},
  "geometry": {"coordinates":[35.06667,32.31667],"type":"Point"}
}