{
  "type": "Feature",
  "properties": {
    "gn:country":"PS",
    "gn:fcode":"PPL",
    "gn:population":2243,
    "iso:country":"PS",
    "name:ara_x_preferred":[
        "\u062c\u064a\u062a"
    ],
    "name:cat_x_preferred":[
        "Jit"
    ],
    "name:eng_x_preferred":[
        "Jit"
    ],
    "name:heb_x_preferred":[
        "\u05d2'\u05d9\u05ea"
    ],
    "name:nld_x_preferred":[
        "Jit"
    ],
    "name:nno_x_preferred":[
        "Jit i Qalqilya"
    ],
    "name:und_x_variant":[
        "Qaryat J\u012bt"
    ],
    "qs_pg:aaroncc":"PS",
    "qs_pg:gn_country":"PS",
    "qs_pg:gn_fcode":"PPL",
    "qs_pg:gn_pop":2243,
    "qs_pg:name":"J\u012bt",
    "qs_pg:photos_9r":0,
    "qs_pg:photos_sr":0,
    "qs_pg:pop_sr":4,
    "qs_pg:qs_pg_placetype":"locality",
    "wof:name":"J\u012bt",
    "wof:placetype":"locality",
    "wof:population":2243
},
  "geometry": {"coordinates":[35.17081,32.21431],"type":"Point"}
}