{
  "type": "Feature",
  "properties": {
    "gn:admin1_code":"00",
    "gn:asciiname":"`Ayn Samyah",
    "gn:country_code":"PS",
    "gn:dem":449,
    "gn:feature_class":"P",
    "gn:feature_code":"PPL",
    "gn:name":"\u2018Ayn S\u0101myah",
    "gn:population":0,
    "gn:timezone":"Asia/Hebron",
    "iso:country":"PS",
    "name:ara_x_preferred":[
        "\u0639\u064a\u0646 \u0633\u0627\u0645\u064a\u0629"
    ],
    "name:und_x_variant":[
        "\u2018Ayn S\u0101myah"
    ],
    "wof:name":"`Ayn Samyah",
    "wof:placetype":"locality"
},
  "geometry": {"coordinates":[35.3338,31.99284],"type":"Point"}
}