{
  "type": "Feature",
  "properties": {
    "gn:gn_country":"PS",
    "gn:gn_fcode":"PPL",
    "gn:gn_pop":366,
    "gn:population":366,
    "iso:country":"PS",
    "name:ara_x_preferred":[
        "\u0623\u0645 \u0627\u0644\u0631\u064a\u062d\u0627\u0646"
    ],
    "name:cat_x_preferred":[
        "Umm ar-Rihan"
    ],
    "name:dut_x_preferred":[
        "Umm ar-Rihan"
    ],
    "name:eng_x_preferred":[
        "Umm ar-Rihan"
    ],
    "name:nno_x_preferred":[
        "Umm ar-Rihan"
    ],
    "name:unk_x_variant":[
        "Khirbat Um er Rih\u0101n"
    ],
    "qs_pg:aaroncc":"PS",
    "qs_pg:gn_country":"PS",
    "qs_pg:gn_fcode":"PPL",
    "qs_pg:gn_pop":366,
    "qs_pg:name":"Umm ar R\u012b\u1e29\u0101n",
    "qs_pg:photos_9r":0,
    "qs_pg:photos_sr":0,
    "qs_pg:pop_sr":2,
    "qs_pg:qs_pg_placetype":"locality",
    "wof:name":"Umm ar R\u012b\u1e29\u0101n",
    "wof:placetype":"locality",
    "wof:population":366
},
  "geometry": {"coordinates":[35.14088,32.48329],"type":"Point"}
}