{
  "type": "Feature",
  "properties": {
    "gn:admin1_code":"WE",
    "gn:admin2_code":"7870653",
    "gn:asciiname":"Dayr Hajalah",
    "gn:country_code":"PS",
    "gn:dem":-323,
    "gn:feature_class":"P",
    "gn:feature_code":"PPL",
    "gn:name":"Dayr \u1e28ajalah",
    "gn:population":0,
    "gn:timezone":"Asia/Hebron",
    "iso:country":"PS",
    "name:ara_x_preferred":[
        "\u062f\u064a\u0631 \u062d\u062c\u0644\u0629"
    ],
    "name:und_x_variant":[
        "Dayr \u1e28ajalah"
    ],
    "wof:name":"Dayr Hajalah",
    "wof:placetype":"locality"
},
  "geometry": {"coordinates":[35.50183,31.82046],"type":"Point"}
}