{
  "type": "Feature",
  "properties": {
    "gn:gn_country":"PS",
    "gn:gn_fcode":"PPL",
    "gn:gn_pop":1391,
    "gn:population":1391,
    "iso:country":"PS",
    "name:ara_x_preferred":[
        "\u062e\u0644\u0629 \u0627\u0644\u0645\u064a\u0629"
    ],
    "name:unk_x_variant":[
        "Khirbat Khallat al Meiya"
    ],
    "qs_pg:aaroncc":"PS",
    "qs_pg:gn_country":"PS",
    "qs_pg:gn_fcode":"PPL",
    "qs_pg:gn_pop":1391,
    "qs_pg:name":"Khallat al Mayyah",
    "qs_pg:photos_9r":0,
    "qs_pg:photos_sr":0,
    "qs_pg:pop_sr":3,
    "qs_pg:qs_pg_placetype":"locality",
    "wof:name":"Khallat al Mayyah",
    "wof:placetype":"locality",
    "wof:population":1391
},
  "geometry": {"coordinates":[35.14286,31.44222],"type":"Point"}
}