{
  "type": "Feature",
  "properties": {
    "gn:gn_country":"PS",
    "gn:gn_fcode":"PPL",
    "gn:gn_pop":267,
    "gn:population":267,
    "iso:country":"PS",
    "name:ara_x_preferred":[
        "\u0641\u0642\u064a\u0642\u064a\u0633"
    ],
    "name:unk_x_variant":[
        "Fuqayq\u012bs"
    ],
    "qs_pg:aaroncc":"PS",
    "qs_pg:gn_country":"PS",
    "qs_pg:gn_fcode":"PPL",
    "qs_pg:gn_pop":267,
    "qs_pg:name":"Fuq\u012bq\u012bs",
    "qs_pg:photos_9r":0,
    "qs_pg:photos_sr":0,
    "qs_pg:pop_sr":2,
    "qs_pg:qs_pg_placetype":"locality",
    "wof:name":"Fuq\u012bq\u012bs",
    "wof:placetype":"locality",
    "wof:population":267
},
  "geometry": {"coordinates":[34.9843,31.48839],"type":"Point"}
}