{
  "type": "Feature",
  "properties": {
    "gn:admin1_code":"WE",
    "gn:admin2_code":"7870653",
    "gn:asciiname":"Khirbat al Mafjir",
    "gn:country_code":"PS",
    "gn:dem":-234,
    "gn:feature_class":"P",
    "gn:feature_code":"PPL",
    "gn:name":"Khirbat al Mafjir",
    "gn:population":0,
    "gn:timezone":"Asia/Hebron",
    "iso:country":"PS",
    "name:und_x_variant":[
        "Qa\u1e63r Hish\u0101m el Amawi",
        "Khirbat el Mafjir",
        "Khirbat al Mafjir"
    ],
    "wof:name":"Khirbat al Mafjir",
    "wof:placetype":"locality"
},
  "geometry": {"coordinates":[35.46175,31.88187000000001],"type":"Point"}
}