{
  "type": "Feature",
  "properties": {
    "gn:gn_country":"PS",
    "gn:gn_fcode":"PPL",
    "gn:gn_pop":4967,
    "gn:population":4967,
    "iso:country":"PS",
    "name:ara_x_preferred":[
        "\u0643\u0641\u0631 \u062f\u0627\u0646"
    ],
    "name:cat_x_preferred":[
        "Kafr Dan"
    ],
    "name:eng_x_preferred":[
        "Kafr Dan"
    ],
    "name:heb_x_preferred":[
        "\u05db\u05e4\u05e8 \u05d3\u05d0\u05df"
    ],
    "name:nld_x_preferred":[
        "Kafr Dan"
    ],
    "name:nno_x_preferred":[
        "Kafr Dan"
    ],
    "name:pol_x_preferred":[
        "Kafr Dan"
    ],
    "name:spa_x_preferred":[
        "Kafr Dan"
    ],
    "qs_pg:aaroncc":"PS",
    "qs_pg:gn_country":"PS",
    "qs_pg:gn_fcode":"PPL",
    "qs_pg:gn_pop":4967,
    "qs_pg:name":"Kafr D\u0101n",
    "qs_pg:photos_9r":0,
    "qs_pg:photos_sr":0,
    "qs_pg:pop_sr":4,
    "qs_pg:qs_pg_placetype":"locality",
    "wof:name":"Kafr D\u0101n",
    "wof:placetype":"locality",
    "wof:population":4967
},
  "geometry": {"coordinates":[35.25425,32.47852],"type":"Point"}
}