{
  "type": "Feature",
  "properties": {
    "gn:admin1_code":"WE",
    "gn:admin2_code":"7870654",
    "gn:asciiname":"Khirbat az Zu`rurah",
    "gn:country_code":"PS",
    "gn:dem":580,
    "gn:feature_class":"P",
    "gn:feature_code":"PPL",
    "gn:name":"Khirbat az Zu\u2018r\u016brah",
    "gn:population":0,
    "gn:timezone":"Asia/Hebron",
    "iso:country":"PS",
    "name:und_x_variant":[
        "Khirbat az Za\u2018r\u016brah",
        "Khirbat ez Za\u2018r\u016bra",
        "Khirbat az Za\u2018rura",
        "Khirbat az Zu\u2018r\u016brah"
    ],
    "wof:name":"Khirbat az Zu`rurah",
    "wof:placetype":"locality"
},
  "geometry": {"coordinates":[35.27399000000001,31.7421],"type":"Point"}
}