{
  "type": "Feature",
  "properties": {
    "gn:country":"PS",
    "gn:fcode":"PPL",
    "gn:population":1107,
    "iso:country":"PS",
    "name:ara_x_preferred":[
        "\u0643\u0641\u0631 \u0635\u0648\u0631"
    ],
    "name:arz_x_preferred":[
        "\u0643\u0641\u0631 \u0635\u0648\u0631"
    ],
    "name:cat_x_preferred":[
        "Kafr Sur"
    ],
    "name:ceb_x_preferred":[
        "Kafr \u015e\u016br"
    ],
    "name:eng_x_preferred":[
        "Kafr Sur"
    ],
    "name:fra_x_preferred":[
        "Kufr Sour"
    ],
    "name:heb_x_preferred":[
        "\u05db\u05e4\u05e8 \u05e1\u05d5\u05e8"
    ],
    "name:nld_x_preferred":[
        "Kafr Sur"
    ],
    "name:nno_x_preferred":[
        "Kafr Sur"
    ],
    "name:pol_x_preferred":[
        "Kafr Sur"
    ],
    "qs_pg:aaroncc":"PS",
    "qs_pg:gn_country":"PS",
    "qs_pg:gn_fcode":"PPL",
    "qs_pg:gn_pop":1107,
    "qs_pg:name":"Kafr \u015e\u016br",
    "qs_pg:photos_9r":0,
    "qs_pg:photos_sr":0,
    "qs_pg:pop_sr":3,
    "qs_pg:qs_pg_placetype":"locality",
    "wof:name":"Kafr \u015e\u016br",
    "wof:placetype":"locality",
    "wof:population":1107
},
  "geometry": {"coordinates":[35.06394,32.24366],"type":"Point"}
}